Workbook

Sheet Dashboard
A1: Customer Transactions Dashboard
A2: ="Data as of "&TEXT(TODAY(),"dd mmm yyyy")&" | Dataset: "&COUNT('Final Project Dataset'!$B$2:$B$251)&" transactions" -> Data as of 30 Oct 2026 | Dataset: 250 transactions
A3: Region (slicer) | B3: South | C3: ◄ Slicer-style drop-downs and date range drive every KPI, table and chart (see HowTo for native Slicers/Timeline).
A4: Product (slicer) | B4: Smartwatch
A5: From date (timeline) | B5: 45658
A6: To date (timeline) | B6: 46022
G7: Top 5 Customers (all time)
A8: VOLUME KPIs | B8: Value | G8: # | H8: Customer | I8: Sales (₹) | J8: Profit (₹) | K8: Txns
A9: Total Sales | B9: =Pivot_Tables!B15 -> 89673 | G9: =High_Value_Customers!M8 -> 1 | H9: =High_Value_Customers!N8 -> Aditya Kapoor | I9: =High_Value_Customers!O8 -> 321673 | J9: =High_Value_Customers!P8 -> 53148.24 | K9: =High_Value_Customers!Q8 -> 6
A10: Total Profit | B10: =Pivot_Tables!C15 -> 15915.68 | G10: =High_Value_Customers!M9 -> 2 | H10: =High_Value_Customers!N9 -> Aditya Mehta | I10: =High_Value_Customers!O9 -> 249362 | J10: =High_Value_Customers!P9 -> 29285.42 | K10: =High_Value_Customers!Q9 -> 6
A11: Transactions | B11: =Pivot_Tables!D15 -> 3 | G11: =High_Value_Customers!M10 -> 3 | H11: =High_Value_Customers!N10 -> Riya Reddy | I11: =High_Value_Customers!O10 -> 237530 | J11: =High_Value_Customers!P10 -> 34908.45 | K11: =High_Value_Customers!Q10 -> 8
A12: Units Sold | B12: =Pivot_Tables!E15 -> 11 | G12: =High_Value_Customers!M11 -> 4 | H12: =High_Value_Customers!N11 -> Priya Iyer | I12: =High_Value_Customers!O11 -> 173827 | J12: =High_Value_Customers!P11 -> 28056.65 | K12: =High_Value_Customers!Q11 -> 4
G13: =High_Value_Customers!M12 -> 5 | H13: =High_Value_Customers!N12 -> Vihaan Mehta | I13: =High_Value_Customers!O12 -> 153202 | J13: =High_Value_Customers!P12 -> 22319.83 | K13: =High_Value_Customers!Q12 -> 7
A14: PERFORMANCE KPI | B14: Actual | C14: Target | D14: Variance | E14: Status
A15: Profit Margin | B15: =IF(B9=0,0,B10/B9) -> 0.17748575 | C15: 0.16 | D15: =IFERROR(B15/C15-1,0) -> 0.10928596 | E15: =IF(D15>=0,"On target",IF(D15>=-0.02,"Watch","Below target")) -> On target
A16: Avg Transaction Value | B16: =IF(B11=0,0,B9/B11) -> 29891 | C16: 20000 | D16: =IFERROR(B16/C16-1,0) -> 0.49455 | E16: =IF(D16>=0,"On target",IF(D16>=-0.02,"Watch","Below target")) -> On target
A17: Avg Profit / Transaction | B17: =IF(B11=0,0,B10/B11) -> 5305.2267 | C17: 3000 | D17: =IFERROR(B17/C17-1,0) -> 0.76840889 | E17: =IF(D17>=0,"On target",IF(D17>=-0.02,"Watch","Below target")) -> On target
A18: Avg Units / Transaction | B18: =IF(B11=0,0,B12/B11) -> 3.6666667 | C18: 2 | D18: =IFERROR(B18/C18-1,0) -> 0.83333333 | E18: =IF(D18>=0,"On target",IF(D18>=-0.02,"Watch","Below target")) -> On target

Sheet Report
B1: Customer Transaction Analysis: Final Report
B2: ="Prepared "&TEXT(TODAY(),"dd mmmm yyyy")&" | All figures below are live formulas over the dataset" -> Prepared 30 October 2026 | All figures below are live formulas over the dataset
J3: Insight engine (supporting calculations)
B4: 1. The big picture | J4: Product | K4: Sales | L4: Profit | M4: Margin
B5: ="Between "&TEXT(MIN('Final Project Dataset'!$B$2:$B$251),"d mmm yyyy")&" and "&TEXT(MAX('Final Project Dataset'!$B$2:$B$251),"d mmm yyyy")&", "&COUNT('Final Project Dataset'!$B$2:$B$251)&" transactions from "&COUNTA(High_Value_Customers!$A$8:$A$86)&" customers generated ₹"&TEXT(SUM('Final Project Dataset'!$F$2:$F$251),"#,##0")&" in sales and ₹"&TEXT(SUM('Final Project Dataset'!$H$2:$H$251),"#,##0")&" in profit, a blended margin of "&TEXT(SUM('Final Project Dataset'!$H$2:$H$251)/SUM('Final Project Dataset'!$F$2:$F$251),"0.0%")&". The average basket is ₹"&TEXT(SUM('Final Project Dataset'!$F$2:$F$251)/COUNT('Final Project Dataset'!$B$2:$B$251),"#,##0")&" with "&TEXT(SUM('Final Project Dataset'!$D$2:$D$251)/COUNT('Final Project Dataset'!$B$2:$B$251),"0.0")&" units per order." -> Between 1 Jan 2025 and 30 Dec 2025, 250 transactions from 79 customers generated ₹5,262,053 in sales and ₹800,178 in profit, a blended margin of 15.2%. The average basket is ₹21,048 with 1.9 units per order. | J5: Laptop | K5: =SUMIF('Final Project Dataset'!$C$2:$C$251,J5,'Final Project Dataset'!$F$2:$F$251) -> 1391226 | L5: =SUMIF('Final Project Dataset'!$C$2:$C$251,J5,'Final Project Dataset'!$H$2:$H$251) -> 203150.95 | M5: =L5/K5 -> 0.14602297
J6: Smartphone | K6: =SUMIF('Final Project Dataset'!$C$2:$C$251,J6,'Final Project Dataset'!$F$2:$F$251) -> 969135 | L6: =SUMIF('Final Project Dataset'!$C$2:$C$251,J6,'Final Project Dataset'!$H$2:$H$251) -> 113001.97 | M6: =L6/K6 -> 0.11660086
B7: 2. Products: revenue vs margin | J7: Monitor | K7: =SUMIF('Final Project Dataset'!$C$2:$C$251,J7,'Final Project Dataset'!$F$2:$F$251) -> 839029 | L7: =SUMIF('Final Project Dataset'!$C$2:$C$251,J7,'Final Project Dataset'!$H$2:$H$251) -> 131567.18 | M7: =L7/K7 -> 0.15680886
B8: ="Revenue is concentrated in a few big-ticket items: "&INDEX(J5:J14,MATCH(MAX(K5:K14),K5:K14,0))&" leads with ₹"&TEXT(MAX(K5:K14),"#,##0")&" ("&TEXT(MAX(K5:K14)/SUM(K5:K14),"0.0%")&" of sales), and the top three products together bring in "&TEXT(LARGE(K5:K14,1)/SUM(K5:K14)+LARGE(K5:K14,2)/SUM(K5:K14)+LARGE(K5:K14,3)/SUM(K5:K14),"0.0%")&" of revenue." -> Revenue is concentrated in a few big-ticket items: Laptop leads with ₹1,391,226 (26.4% of sales), and the top three products together bring in 60.8% of revenue. | J8: Tablet | K8: =SUMIF('Final Project Dataset'!$C$2:$C$251,J8,'Final Project Dataset'!$F$2:$F$251) -> 812944 | L8: =SUMIF('Final Project Dataset'!$C$2:$C$251,J8,'Final Project Dataset'!$H$2:$H$251) -> 97842.31 | M8: =L8/K8 -> 0.12035553
B9: ="Margin tells a different story: "&INDEX(J5:J14,MATCH(MAX(M5:M14),M5:M14,0))&" earns the best margin ("&TEXT(MAX(M5:M14),"0.0%")&") while "&INDEX(J5:J14,MATCH(MIN(M5:M14),M5:M14,0))&" earns the lowest ("&TEXT(MIN(M5:M14),"0.0%")&"). "&IF(ISNUMBER(FIND(",",Frequency_Match!B15)),"The most frequently purchased products are "&Frequency_Match!B15&" (tied at "&Frequency_Match!B16&" transactions each)","The most frequently purchased product is "&Frequency_Match!B15&" ("&Frequency_Match!B16&" transactions)")&", so purchase frequency and revenue are driven by different items." -> Margin tells a different story: Mouse earns the best margin (29.5%) while Smartphone earns the lowest (11.7%). The most frequently purchased products are Monitor, Headphones (tied at 30 transactions each), so purchase frequency and revenue are driven by different items. | J9: Smartwatch | K9: =SUMIF('Final Project Dataset'!$C$2:$C$251,J9,'Final Project Dataset'!$F$2:$F$251) -> 451804 | L9: =SUMIF('Final Project Dataset'!$C$2:$C$251,J9,'Final Project Dataset'!$H$2:$H$251) -> 80562.49 | M9: =L9/K9 -> 0.17831292
J10: Printer | K10: =SUMIF('Final Project Dataset'!$C$2:$C$251,J10,'Final Project Dataset'!$F$2:$F$251) -> 323199 | L10: =SUMIF('Final Project Dataset'!$C$2:$C$251,J10,'Final Project Dataset'!$H$2:$H$251) -> 53932.62 | M10: =L10/K10 -> 0.16687125
B11: 3. Regions and timing | J11: Headphones | K11: =SUMIF('Final Project Dataset'!$C$2:$C$251,J11,'Final Project Dataset'!$F$2:$F$251) -> 190247 | L11: =SUMIF('Final Project Dataset'!$C$2:$C$251,J11,'Final Project Dataset'!$H$2:$H$251) -> 49532.28 | M11: =L11/K11 -> 0.26035775
B12: ="By region, "&INDEX(J18:J22,MATCH(MAX(K18:K22),K18:K22,0))&" is the strongest market (₹"&TEXT(MAX(K18:K22),"#,##0")&") and "&INDEX(J18:J22,MATCH(MIN(K18:K22),K18:K22,0))&" the weakest (₹"&TEXT(MIN(K18:K22),"#,##0")&"), a gap of "&TEXT(MAX(K18:K22)/MIN(K18:K22)-1,"0%")&"." -> By region, West is the strongest market (₹1,391,841) and North the weakest (₹852,561), a gap of 63%. | J12: Webcam | K12: =SUMIF('Final Project Dataset'!$C$2:$C$251,J12,'Final Project Dataset'!$F$2:$F$251) -> 155853 | L12: =SUMIF('Final Project Dataset'!$C$2:$C$251,J12,'Final Project Dataset'!$H$2:$H$251) -> 33233.14 | M12: =L12/K12 -> 0.21323388
B13: ="Sales are seasonal: "&TEXT(INDEX(J26:J37,MATCH(MAX(K26:K37),K26:K37,0)),"mmmm")&" is the peak month (₹"&TEXT(MAX(K26:K37),"#,##0")&") and "&TEXT(INDEX(J26:J37,MATCH(MIN(K26:K37),K26:K37,0)),"mmmm")&" the trough (₹"&TEXT(MIN(K26:K37),"#,##0")&"). The most used payment channel by value is "&INDEX(J41:J45,MATCH(MAX(K41:K45),K41:K45,0))&" ("&TEXT(MAX(K41:K45)/SUM(K41:K45),"0%")&" of sales)." -> Sales are seasonal: March is the peak month (₹962,449) and September the trough (₹157,693). The most used payment channel by value is Net Banking (28% of sales). | J13: Keyboard | K13: =SUMIF('Final Project Dataset'!$C$2:$C$251,J13,'Final Project Dataset'!$F$2:$F$251) -> 89109 | L13: =SUMIF('Final Project Dataset'!$C$2:$C$251,J13,'Final Project Dataset'!$H$2:$H$251) -> 25713.01 | M13: =L13/K13 -> 0.28855682
J14: Mouse | K14: =SUMIF('Final Project Dataset'!$C$2:$C$251,J14,'Final Project Dataset'!$F$2:$F$251) -> 39507 | L14: =SUMIF('Final Project Dataset'!$C$2:$C$251,J14,'Final Project Dataset'!$H$2:$H$251) -> 11642.31 | M14: =L14/K14 -> 0.2946898
B15: 4. Customers
B16: ="The top "&TEXT(1-High_Value_Customers!B3,"0%")&" of customers ("&High_Value_Customers!E3&" people with at least ₹"&TEXT(High_Value_Customers!B4,"#,##0")&" in purchases) deliver "&TEXT(High_Value_Customers!E4,"0.0%")&" of all sales, so a small group carries a large part of revenue." -> The top 20% of customers (16 people with at least ₹100,178 in purchases) deliver 46.2% of all sales, so a small group carries a large part of revenue.
B17: ="The biggest customer is "&High_Value_Customers!N8&" with ₹"&TEXT(High_Value_Customers!O8,"#,##0")&" across "&High_Value_Customers!Q8&" purchases. "&Frequency_Match!B19&" customers bought more than once, and "&TEXT(Frequency_Match!B22,"0%")&" of transactions come from repeat names; the most frequent buyer is "&Frequency_Match!B20&" ("&Frequency_Match!B21&" purchases)." -> The biggest customer is Aditya Kapoor with ₹321,673 across 6 purchases. 70 customers bought more than once, and 96% of transactions come from repeat names; the most frequent buyer is Riya Reddy (8 purchases). | J17: Region | K17: Sales | L17: Profit
J18: North | K18: =SUMIF('Final Project Dataset'!$G$2:$G$251,J18,'Final Project Dataset'!$F$2:$F$251) -> 852561 | L18: =SUMIF('Final Project Dataset'!$G$2:$G$251,J18,'Final Project Dataset'!$H$2:$H$251) -> 132198.05
B19: 5. What drives profit (regression) | J19: South | K19: =SUMIF('Final Project Dataset'!$G$2:$G$251,J19,'Final Project Dataset'!$F$2:$F$251) -> 907263 | L19: =SUMIF('Final Project Dataset'!$G$2:$G$251,J19,'Final Project Dataset'!$H$2:$H$251) -> 130463.13
B20: ="Profit rises steadily with sales: each extra ₹1,000 of sales adds about ₹"&TEXT(Regression!B18*1000,"#,##0")&" of profit, and sales alone explain "&TEXT(Regression!B5,"0.0%")&" of profit variation (significance F = "&TEXT(Regression!F12,"0.0E+00")&"). Because the relationship is so strong, growing order value is a reliable profit lever; the gap to a perfect fit comes from product mix, since margins differ by product." -> Profit rises steadily with sales: each extra ₹1,000 of sales adds about ₹137 of profit, and sales alone explain 89.3% of profit variation (significance F = 1.3E-122). Because the relationship is so strong, growing order value is a reliable profit lever; the gap to a perfect fit comes from product mix, since margins differ by product. | J20: East | K20: =SUMIF('Final Project Dataset'!$G$2:$G$251,J20,'Final Project Dataset'!$F$2:$F$251) -> 877262 | L20: =SUMIF('Final Project Dataset'!$G$2:$G$251,J20,'Final Project Dataset'!$H$2:$H$251) -> 117002.59
J21: West | K21: =SUMIF('Final Project Dataset'!$G$2:$G$251,J21,'Final Project Dataset'!$F$2:$F$251) -> 1391841 | L21: =SUMIF('Final Project Dataset'!$G$2:$G$251,J21,'Final Project Dataset'!$H$2:$H$251) -> 224254.78
B22: 6. What-if outlook | J22: Central | K22: =SUMIF('Final Project Dataset'!$G$2:$G$251,J22,'Final Project Dataset'!$F$2:$F$251) -> 1233126 | L22: =SUMIF('Final Project Dataset'!$G$2:$G$251,J22,'Final Project Dataset'!$H$2:$H$251) -> 196259.71
B23: ="Baseline profit is ₹"&TEXT(WhatIf!B5,"#,##0")&". In the optimistic scenario (price "&TEXT(WhatIf!F5,"+0%;-0%")&", volume "&TEXT(WhatIf!F6,"+0%;-0%")&", cost "&TEXT(WhatIf!F7,"+0%;-0%")&") profit would be ₹"&TEXT(WhatIf!F11,"#,##0")&" ("&TEXT(WhatIf!F13,"+0%;-0%")&"); in the pessimistic one it falls to ₹"&TEXT(WhatIf!G11,"#,##0")&" ("&TEXT(WhatIf!G13,"+0%;-0%")&"). To lift profit by "&TEXT(WhatIf!B24,"0%")&" through volume alone, sales volume must grow by "&TEXT(WhatIf!B26,"0.0%")&"." -> Baseline profit is ₹800,178. In the optimistic scenario (price +5%, volume +10%, cost -3%) profit would be ₹1,316,851 (+65%); in the pessimistic one it falls to ₹282,584 (-65%). To lift profit by 20% through volume alone, sales volume must grow by 20.0%.
B25: 7. Recommendations (based on the data as delivered) | J25: Month | K25: Sales
B26: • Protect margin on high-revenue, low-margin lines. Smartphones and Tablets bring in large revenue but earn the thinnest margins (about 12%), so discount discipline there pays off quickly. | J26: =DATE(2025,1,1) -> 45658 | K26: =SUMIFS('Final Project Dataset'!$F$2:$F$251,'Final Project Dataset'!$B$2:$B$251,">="&J26,'Final Project Dataset'!$B$2:$B$251,"<="&EOMONTH(J26,0)) -> 246721
B27: • Bundle high-margin accessories (Keyboards, Mice, Headphones earn 26–29%) with Laptops and Monitors to raise margin per order without needing more customers. | J27: =EDATE(J26,1) -> 45689 | K27: =SUMIFS('Final Project Dataset'!$F$2:$F$251,'Final Project Dataset'!$B$2:$B$251,">="&J27,'Final Project Dataset'!$B$2:$B$251,"<="&EOMONTH(J27,0)) -> 431916
B28: ="• Build a retention programme for the top customers: the top "&TEXT(1-High_Value_Customers!B3,"0%")&" of buyers drive "&TEXT(High_Value_Customers!E4,"0%")&" of sales, and repeat buyers are the cheapest revenue to grow." -> • Build a retention programme for the top customers: the top 20% of buyers drive 46% of sales, and repeat buyers are the cheapest revenue to grow. | J28: =EDATE(J27,1) -> 45717 | K28: =SUMIFS('Final Project Dataset'!$F$2:$F$251,'Final Project Dataset'!$B$2:$B$251,">="&J28,'Final Project Dataset'!$B$2:$B$251,"<="&EOMONTH(J28,0)) -> 962449
B29: • Lift the weakest region with targeted campaigns, and plan stock and promotions around the March peak and the September dip. | J29: =EDATE(J28,1) -> 45748 | K29: =SUMIFS('Final Project Dataset'!$F$2:$F$251,'Final Project Dataset'!$B$2:$B$251,">="&J29,'Final Project Dataset'!$B$2:$B$251,"<="&EOMONTH(J29,0)) -> 180954
J30: =EDATE(J29,1) -> 45778 | K30: =SUMIFS('Final Project Dataset'!$F$2:$F$251,'Final Project Dataset'!$B$2:$B$251,">="&J30,'Final Project Dataset'!$B$2:$B$251,"<="&EOMONTH(J30,0)) -> 418176
B31: 8. Method | J31: =EDATE(J30,1) -> 45809 | K31: =SUMIFS('Final Project Dataset'!$F$2:$F$251,'Final Project Dataset'!$B$2:$B$251,">="&J31,'Final Project Dataset'!$B$2:$B$251,"<="&EOMONTH(J31,0)) -> 331705
B32: Data: 250 transactions (Final Project Dataset sheet). Analysis uses SUMIFS/COUNTIFS pivot-style tables, INDEX/MATCH multi-value filtering, DATEDIF/EOMONTH date logic, and LINEST-equivalent regression formulas. Dashboard filters (drop-downs and date range) work like Slicers and a Timeline; see HowTo for the native Excel versions. | J32: =EDATE(J31,1) -> 45839 | K32: =SUMIFS('Final Project Dataset'!$F$2:$F$251,'Final Project Dataset'!$B$2:$B$251,">="&J32,'Final Project Dataset'!$B$2:$B$251,"<="&EOMONTH(J32,0)) -> 488558
J33: =EDATE(J32,1) -> 45870 | K33: =SUMIFS('Final Project Dataset'!$F$2:$F$251,'Final Project Dataset'!$B$2:$B$251,">="&J33,'Final Project Dataset'!$B$2:$B$251,"<="&EOMONTH(J33,0)) -> 516837
J34: =EDATE(J33,1) -> 45901 | K34: =SUMIFS('Final Project Dataset'!$F$2:$F$251,'Final Project Dataset'!$B$2:$B$251,">="&J34,'Final Project Dataset'!$B$2:$B$251,"<="&EOMONTH(J34,0)) -> 157693
J35: =EDATE(J34,1) -> 45931 | K35: =SUMIFS('Final Project Dataset'!$F$2:$F$251,'Final Project Dataset'!$B$2:$B$251,">="&J35,'Final Project Dataset'!$B$2:$B$251,"<="&EOMONTH(J35,0)) -> 442217
J36: =EDATE(J35,1) -> 45962 | K36: =SUMIFS('Final Project Dataset'!$F$2:$F$251,'Final Project Dataset'!$B$2:$B$251,">="&J36,'Final Project Dataset'!$B$2:$B$251,"<="&EOMONTH(J36,0)) -> 499395
J37: =EDATE(J36,1) -> 45992 | K37: =SUMIFS('Final Project Dataset'!$F$2:$F$251,'Final Project Dataset'!$B$2:$B$251,">="&J37,'Final Project Dataset'!$B$2:$B$251,"<="&EOMONTH(J37,0)) -> 585432
J40: Payment | K40: Sales
J41: Credit Card | K41: =SUMIF('Final Project Dataset'!$J$2:$J$251,J41,'Final Project Dataset'!$F$2:$F$251) -> 1260631
J42: Debit Card | K42: =SUMIF('Final Project Dataset'!$J$2:$J$251,J42,'Final Project Dataset'!$F$2:$F$251) -> 626766
J43: UPI | K43: =SUMIF('Final Project Dataset'!$J$2:$J$251,J43,'Final Project Dataset'!$F$2:$F$251) -> 1053936
J44: Cash | K44: =SUMIF('Final Project Dataset'!$J$2:$J$251,J44,'Final Project Dataset'!$F$2:$F$251) -> 844615
J45: Net Banking | K45: =SUMIF('Final Project Dataset'!$J$2:$J$251,J45,'Final Project Dataset'!$F$2:$F$251) -> 1476105

Sheet Final Project Dataset
A1: transaction_id | B1: date | C1: product | D1: quantity | E1: unit_price | F1: sales | G1: region | H1: profit | I1: customer_id | J1: payment_method | K1: customer_name | L1: Month End (EOMONTH) | M1: Months Ago (DATEDIF) | N1: Days Ago (TODAY) | O1: Profit Margin | P1: Customer Type | Q1: Txn Code | R1: Initials | S1: Filter Flag | T1: Filter Match #
A2: T0001 | B2: 45658 | C2: Headphones | D2: 2 | E2: 3695 | F2: 7390 | G2: Central | H2: 1869.93 | I2: C042 | J2: Cash | K2: Priya Sharma | L2: =EOMONTH(B2,0) -> 45688 | M2: =DATEDIF(B2,TODAY(),"m") -> 21 | N2: =TODAY()-B2 -> 667 | O2: =IF(F2=0,0,H2/F2) -> 0.25303518 | P2: =IF(COUNTIF($K$2:$K$251,K2)>1,"Repeat","One-time") -> Repeat | Q2: =UPPER(LEFT(C2,3))&"-"&TEXT(B2,"MMYY")&"-"&TEXT(F2,"00000") -> HEA-0125-07390 | R2: =LEFT(K2,1)&MID(K2,FIND(" ",K2)+1,1) -> PS | S2: =IF(AND(OR(FILTER_Demo!$B$3="All",G2=FILTER_Demo!$B$3),OR(FILTER_Demo!$B$4="All",C2=FILTER_Demo!$B$4),F2>=FILTER_Demo!$B$5),1,0) -> 0 | T2: =IF(S2=1,SUM($S$2:S2),"")
A3: T0002 | B3: 45661 | C3: Printer | D3: 1 | E3: 9403 | F3: 9403 | G3: South | H3: 1295.91 | I3: C055 | J3: UPI | K3: Pooja Iyer | L3: =EOMONTH(B3,0) -> 45688 | M3: =DATEDIF(B3,TODAY(),"m") -> 21 | N3: =TODAY()-B3 -> 664 | O3: =IF(F3=0,0,H3/F3) -> 0.13781878 | P3: =IF(COUNTIF($K$2:$K$251,K3)>1,"Repeat","One-time") -> Repeat | Q3: =UPPER(LEFT(C3,3))&"-"&TEXT(B3,"MMYY")&"-"&TEXT(F3,"00000") -> PRI-0125-09403 | R3: =LEFT(K3,1)&MID(K3,FIND(" ",K3)+1,1) -> PI | S3: =IF(AND(OR(FILTER_Demo!$B$3="All",G3=FILTER_Demo!$B$3),OR(FILTER_Demo!$B$4="All",C3=FILTER_Demo!$B$4),F3>=FILTER_Demo!$B$5),1,0) -> 0 | T3: =IF(S3=1,SUM($S$2:S3),"")
A4: T0003 | B4: 45661 | C4: Tablet | D4: 2 | E4: 17312 | F4: 34624 | G4: South | H4: 3946.53 | I4: C019 | J4: Net Banking | K4: Aditya Trivedi | L4: =EOMONTH(B4,0) -> 45688 | M4: =DATEDIF(B4,TODAY(),"m") -> 21 | N4: =TODAY()-B4 -> 664 | O4: =IF(F4=0,0,H4/F4) -> 0.1139825 | P4: =IF(COUNTIF($K$2:$K$251,K4)>1,"Repeat","One-time") -> Repeat | Q4: =UPPER(LEFT(C4,3))&"-"&TEXT(B4,"MMYY")&"-"&TEXT(F4,"00000") -> TAB-0125-34624 | R4: =LEFT(K4,1)&MID(K4,FIND(" ",K4)+1,1) -> AT | S4: =IF(AND(OR(FILTER_Demo!$B$3="All",G4=FILTER_Demo!$B$3),OR(FILTER_Demo!$B$4="All",C4=FILTER_Demo!$B$4),F4>=FILTER_Demo!$B$5),1,0) -> 1 | T4: =IF(S4=1,SUM($S$2:S4),"") -> 1
A5: T0004 | B5: 45665 | C5: Webcam | D5: 3 | E5: 2917 | F5: 8751 | G5: Central | H5: 1759.61 | I5: C053 | J5: Credit Card | K5: Manish Nair | L5: =EOMONTH(B5,0) -> 45688 | M5: =DATEDIF(B5,TODAY(),"m") -> 21 | N5: =TODAY()-B5 -> 660 | O5: =IF(F5=0,0,H5/F5) -> 0.20107531 | P5: =IF(COUNTIF($K$2:$K$251,K5)>1,"Repeat","One-time") -> Repeat | Q5: =UPPER(LEFT(C5,3))&"-"&TEXT(B5,"MMYY")&"-"&TEXT(F5,"00000") -> WEB-0125-08751 | R5: =LEFT(K5,1)&MID(K5,FIND(" ",K5)+1,1) -> MN | S5: =IF(AND(OR(FILTER_Demo!$B$3="All",G5=FILTER_Demo!$B$3),OR(FILTER_Demo!$B$4="All",C5=FILTER_Demo!$B$4),F5>=FILTER_Demo!$B$5),1,0) -> 0 | T5: =IF(S5=1,SUM($S$2:S5),"")
A6: T0005 | B6: 45668 | C6: Smartwatch | D6: 5 | E6: 8538 | F6: 42690 | G6: East | H6: 8005.22 | I6: C074 | J6: Credit Card | K6: Anjali Bhatt | L6: =EOMONTH(B6,0) -> 45688 | M6: =DATEDIF(B6,TODAY(),"m") -> 21 | N6: =TODAY()-B6 -> 657 | O6: =IF(F6=0,0,H6/F6) -> 0.18751979 | P6: =IF(COUNTIF($K$2:$K$251,K6)>1,"Repeat","One-time") -> Repeat | Q6: =UPPER(LEFT(C6,3))&"-"&TEXT(B6,"MMYY")&"-"&TEXT(F6,"00000") -> SMA-0125-42690 | R6: =LEFT(K6,1)&MID(K6,FIND(" ",K6)+1,1) -> AB | S6: =IF(AND(OR(FILTER_Demo!$B$3="All",G6=FILTER_Demo!$B$3),OR(FILTER_Demo!$B$4="All",C6=FILTER_Demo!$B$4),F6>=FILTER_Demo!$B$5),1,0) -> 0 | T6: =IF(S6=1,SUM($S$2:S6),"")
A7: T0006 | B7: 45670 | C7: Headphones | D7: 5 | E7: 3718 | F7: 18590 | G7: South | H7: 5356.55 | I7: C043 | J7: Cash | K7: Amit Trivedi | L7: =EOMONTH(B7,0) -> 45688 | M7: =DATEDIF(B7,TODAY(),"m") -> 21 | N7: =TODAY()-B7 -> 655 | O7: =IF(F7=0,0,H7/F7) -> 0.28814147 | P7: =IF(COUNTIF($K$2:$K$251,K7)>1,"Repeat","One-time") -> Repeat | Q7: =UPPER(LEFT(C7,3))&"-"&TEXT(B7,"MMYY")&"-"&TEXT(F7,"00000") -> HEA-0125-18590 | R7: =LEFT(K7,1)&MID(K7,FIND(" ",K7)+1,1) -> AT | S7: =IF(AND(OR(FILTER_Demo!$B$3="All",G7=FILTER_Demo!$B$3),OR(FILTER_Demo!$B$4="All",C7=FILTER_Demo!$B$4),F7>=FILTER_Demo!$B$5),1,0) -> 0 | T7: =IF(S7=1,SUM($S$2:S7),"")
A8: T0007 | B8: 45672 | C8: Keyboard | D8: 1 | E8: 1978 | F8: 1978 | G8: East | H8: 529.1 | I8: C013 | J8: UPI | K8: Vihaan Mehta | L8: =EOMONTH(B8,0) -> 45688 | M8: =DATEDIF(B8,TODAY(),"m") -> 21 | N8: =TODAY()-B8 -> 653 | O8: =IF(F8=0,0,H8/F8) -> 0.26749242 | P8: =IF(COUNTIF($K$2:$K$251,K8)>1,"Repeat","One-time") -> Repeat | Q8: =UPPER(LEFT(C8,3))&"-"&TEXT(B8,"MMYY")&"-"&TEXT(F8,"00000") -> KEY-0125-01978 | R8: =LEFT(K8,1)&MID(K8,FIND(" ",K8)+1,1) -> VM | S8: =IF(AND(OR(FILTER_Demo!$B$3="All",G8=FILTER_Demo!$B$3),OR(FILTER_Demo!$B$4="All",C8=FILTER_Demo!$B$4),F8>=FILTER_Demo!$B$5),1,0) -> 0 | T8: =IF(S8=1,SUM($S$2:S8),"")
A9: T0008 | B9: 45672 | C9: Keyboard | D9: 3 | E9: 1823 | F9: 5469 | G9: North | H9: 1709.19 | I9: C006 | J9: Net Banking | K9: Riya Shah | L9: =EOMONTH(B9,0) -> 45688 | M9: =DATEDIF(B9,TODAY(),"m") -> 21 | N9: =TODAY()-B9 -> 653 | O9: =IF(F9=0,0,H9/F9) -> 0.31252331 | P9: =IF(COUNTIF($K$2:$K$251,K9)>1,"Repeat","One-time") -> Repeat | Q9: =UPPER(LEFT(C9,3))&"-"&TEXT(B9,"MMYY")&"-"&TEXT(F9,"00000") -> KEY-0125-05469 | R9: =LEFT(K9,1)&MID(K9,FIND(" ",K9)+1,1) -> RS | S9: =IF(AND(OR(FILTER_Demo!$B$3="All",G9=FILTER_Demo!$B$3),OR(FILTER_Demo!$B$4="All",C9=FILTER_Demo!$B$4),F9>=FILTER_Demo!$B$5),1,0) -> 0 | T9: =IF(S9=1,SUM($S$2:S9),"")
A10: T0009 | B10: 45674 | C10: Laptop | D10: 1 | E10: 46180 | F10: 46180 | G10: East | H10: 5213.45 | I10: C010 | J10: Net Banking | K10: Vihaan Bhatt | L10: =EOMONTH(B10,0) -> 45688 | M10: =DATEDIF(B10,TODAY(),"m") -> 21 | N10: =TODAY()-B10 -> 651 | O10: =IF(F10=0,0,H10/F10) -> 0.11289411 | P10: =IF(COUNTIF($K$2:$K$251,K10)>1,"Repeat","One-time") -> Repeat | Q10: =UPPER(LEFT(C10,3))&"-"&TEXT(B10,"MMYY")&"-"&TEXT(F10,"00000") -> LAP-0125-46180 | R10: =LEFT(K10,1)&MID(K10,FIND(" ",K10)+1,1) -> VB | S10: =IF(AND(OR(FILTER_Demo!$B$3="All",G10=FILTER_Demo!$B$3),OR(FILTER_Demo!$B$4="All",C10=FILTER_Demo!$B$4),F10>=FILTER_Demo!$B$5),1,0) -> 0 | T10: =IF(S10=1,SUM($S$2:S10),"")
A11: T0010 | B11: 45677 | C11: Smartwatch | D11: 1 | E11: 8460 | F11: 8460 | G11: West | H11: 1191.25 | I11: C029 | J11: Debit Card | K11: Vihaan Iyer | L11: =EOMONTH(B11,0) -> 45688 | M11: =DATEDIF(B11,TODAY(),"m") -> 21 | N11: =TODAY()-B11 -> 648 | O11: =IF(F11=0,0,H11/F11) -> 0.14080969 | P11: =IF(COUNTIF($K$2:$K$251,K11)>1,"Repeat","One-time") -> Repeat | Q11: =UPPER(LEFT(C11,3))&"-"&TEXT(B11,"MMYY")&"-"&TEXT(F11,"00000") -> SMA-0125-08460 | R11: =LEFT(K11,1)&MID(K11,FIND(" ",K11)+1,1) -> VI | S11: =IF(AND(OR(FILTER_Demo!$B$3="All",G11=FILTER_Demo!$B$3),OR(FILTER_Demo!$B$4="All",C11=FILTER_Demo!$B$4),F11>=FILTER_Demo!$B$5),1,0) -> 0 | T11: =IF(S11=1,SUM($S$2:S11),"")
A12: T0011 | B12: 45679 | C12: Webcam | D12: 3 | E12: 2966 | F12: 8898 | G12: East | H12: 2016.23 | I12: C069 | J12: Cash | K12: Aditya Reddy | L12: =EOMONTH(B12,0) -> 45688 | M12: =DATEDIF(B12,TODAY(),"m") -> 21 | N12: =TODAY()-B12 -> 646 | O12: =IF(F12=0,0,H12/F12) -> 0.22659362 | P12: =IF(COUNTIF($K$2:$K$251,K12)>1,"Repeat","One-time") -> Repeat | Q12: =UPPER(LEFT(C12,3))&"-"&TEXT(B12,"MMYY")&"-"&TEXT(F12,"00000") -> WEB-0125-08898 | R12: =LEFT(K12,1)&MID(K12,FIND(" ",K12)+1,1) -> AR | S12: =IF(AND(OR(FILTER_Demo!$B$3="All",G12=FILTER_Demo!$B$3),OR(FILTER_Demo!$B$4="All",C12=FILTER_Demo!$B$4),F12>=FILTER_Demo!$B$5),1,0) -> 0 | T12: =IF(S12=1,SUM($S$2:S12),"")
A13: T0012 | B13: 45679 | C13: Webcam | D13: 2 | E13: 2735 | F13: 5470 | G13: West | H13: 1247.34 | I13: C074 | J13: Debit Card | K13: Anjali Bhatt | L13: =EOMONTH(B13,0) -> 45688 | M13: =DATEDIF(B13,TODAY(),"m") -> 21 | N13: =TODAY()-B13 -> 646 | O13: =IF(F13=0,0,H13/F13) -> 0.22803291 | P13: =IF(COUNTIF($K$2:$K$251,K13)>1,"Repeat","One-time") -> Repeat | Q13: =UPPER(LEFT(C13,3))&"-"&TEXT(B13,"MMYY")&"-"&TEXT(F13,"00000") -> WEB-0125-05470 | R13: =LEFT(K13,1)&MID(K13,FIND(" ",K13)+1,1) -> AB | S13: =IF(AND(OR(FILTER_Demo!$B$3="All",G13=FILTER_Demo!$B$3),OR(FILTER_Demo!$B$4="All",C13=FILTER_Demo!$B$4),F13>=FILTER_Demo!$B$5),1,0) -> 0 | T13: =IF(S13=1,SUM($S$2:S13),"")
... A251: T0250 | B251: 46021 | C251: Printer | D251: 1 | E251: 9120 | F251: 9120 | G251: South | H251: 1146.84 | I251: C047 | J251: Net Banking | K251: Priya Iyer | L251: =EOMONTH(B251,0) -> 46022 | M251: =DATEDIF(B251,TODAY(),"m") -> 10 | N251: =TODAY()-B251 -> 304 | O251: =IF(F251=0,0,H251/F251) -> 0.12575 | P251: =IF(COUNTIF($K$2:$K$251,K251)>1,"Repeat","One-time") -> Repeat | Q251: =UPPER(LEFT(C251,3))&"-"&TEXT(B251,"MMYY")&"-"&TEXT(F251,"00000") -> PRI-1225-09120 | R251: =LEFT(K251,1)&MID(K251,FIND(" ",K251)+1,1) -> PI | S251: =IF(AND(OR(FILTER_Demo!$B$3="All",G251=FILTER_Demo!$B$3),OR(FILTER_Demo!$B$4="All",C251=FILTER_Demo!$B$4),F251>=FILTER_Demo!$B$5),1,0) -> 0 | T251: =IF(S251=1,SUM($S$2:S251),"")

Sheet Pivot_Tables
A1: Pivot-Style Summary Tables (SUMIFS / COUNTIFS) | H1: Filter criteria (from Dashboard)
A2: Responds to the filters on the Dashboard. Source for all dashboard charts. | H2: Region | I2: =IF(Dashboard!$B$3="All","*",Dashboard!$B$3) -> South
A3: By Product | H3: Product | I3: =IF(Dashboard!$B$4="All","*",Dashboard!$B$4) -> Smartwatch
A4: Product | B4: Sales (₹) | C4: Profit (₹) | D4: Transactions | E4: Units | H4: From | I4: =Dashboard!$B$5 -> 45658
A5: Laptop | B5: =SUMIFS('Final Project Dataset'!$F$2:$F$251,'Final Project Dataset'!$C$2:$C$251,$A5,'Final Project Dataset'!$G$2:$G$251,$I$2,'Final Project Dataset'!$C$2:$C$251,$I$3,'Final Project Dataset'!$B$2:$B$251,">="&$I$4,'Final Project Dataset'!$B$2:$B$251,"<="&$I$5) -> 0 | C5: =SUMIFS('Final Project Dataset'!$H$2:$H$251,'Final Project Dataset'!$C$2:$C$251,$A5,'Final Project Dataset'!$G$2:$G$251,$I$2,'Final Project Dataset'!$C$2:$C$251,$I$3,'Final Project Dataset'!$B$2:$B$251,">="&$I$4,'Final Project Dataset'!$B$2:$B$251,"<="&$I$5) -> 0 | D5: =COUNTIFS('Final Project Dataset'!$C$2:$C$251,$A5,'Final Project Dataset'!$G$2:$G$251,$I$2,'Final Project Dataset'!$C$2:$C$251,$I$3,'Final Project Dataset'!$B$2:$B$251,">="&$I$4,'Final Project Dataset'!$B$2:$B$251,"<="&$I$5) -> 0 | E5: =SUMIFS('Final Project Dataset'!$D$2:$D$251,'Final Project Dataset'!$C$2:$C$251,$A5,'Final Project Dataset'!$G$2:$G$251,$I$2,'Final Project Dataset'!$C$2:$C$251,$I$3,'Final Project Dataset'!$B$2:$B$251,">="&$I$4,'Final Project Dataset'!$B$2:$B$251,"<="&$I$5) -> 0 | H5: To | I5: =Dashboard!$B$6 -> 46022
A6: Smartphone | B6: =SUMIFS('Final Project Dataset'!$F$2:$F$251,'Final Project Dataset'!$C$2:$C$251,$A6,'Final Project Dataset'!$G$2:$G$251,$I$2,'Final Project Dataset'!$C$2:$C$251,$I$3,'Final Project Dataset'!$B$2:$B$251,">="&$I$4,'Final Project Dataset'!$B$2:$B$251,"<="&$I$5) -> 0 | C6: =SUMIFS('Final Project Dataset'!$H$2:$H$251,'Final Project Dataset'!$C$2:$C$251,$A6,'Final Project Dataset'!$G$2:$G$251,$I$2,'Final Project Dataset'!$C$2:$C$251,$I$3,'Final Project Dataset'!$B$2:$B$251,">="&$I$4,'Final Project Dataset'!$B$2:$B$251,"<="&$I$5) -> 0 | D6: =COUNTIFS('Final Project Dataset'!$C$2:$C$251,$A6,'Final Project Dataset'!$G$2:$G$251,$I$2,'Final Project Dataset'!$C$2:$C$251,$I$3,'Final Project Dataset'!$B$2:$B$251,">="&$I$4,'Final Project Dataset'!$B$2:$B$251,"<="&$I$5) -> 0 | E6: =SUMIFS('Final Project Dataset'!$D$2:$D$251,'Final Project Dataset'!$C$2:$C$251,$A6,'Final Project Dataset'!$G$2:$G$251,$I$2,'Final Project Dataset'!$C$2:$C$251,$I$3,'Final Project Dataset'!$B$2:$B$251,">="&$I$4,'Final Project Dataset'!$B$2:$B$251,"<="&$I$5) -> 0
A7: Monitor | B7: =SUMIFS('Final Project Dataset'!$F$2:$F$251,'Final Project Dataset'!$C$2:$C$251,$A7,'Final Project Dataset'!$G$2:$G$251,$I$2,'Final Project Dataset'!$C$2:$C$251,$I$3,'Final Project Dataset'!$B$2:$B$251,">="&$I$4,'Final Project Dataset'!$B$2:$B$251,"<="&$I$5) -> 0 | C7: =SUMIFS('Final Project Dataset'!$H$2:$H$251,'Final Project Dataset'!$C$2:$C$251,$A7,'Final Project Dataset'!$G$2:$G$251,$I$2,'Final Project Dataset'!$C$2:$C$251,$I$3,'Final Project Dataset'!$B$2:$B$251,">="&$I$4,'Final Project Dataset'!$B$2:$B$251,"<="&$I$5) -> 0 | D7: =COUNTIFS('Final Project Dataset'!$C$2:$C$251,$A7,'Final Project Dataset'!$G$2:$G$251,$I$2,'Final Project Dataset'!$C$2:$C$251,$I$3,'Final Project Dataset'!$B$2:$B$251,">="&$I$4,'Final Project Dataset'!$B$2:$B$251,"<="&$I$5) -> 0 | E7: =SUMIFS('Final Project Dataset'!$D$2:$D$251,'Final Project Dataset'!$C$2:$C$251,$A7,'Final Project Dataset'!$G$2:$G$251,$I$2,'Final Project Dataset'!$C$2:$C$251,$I$3,'Final Project Dataset'!$B$2:$B$251,">="&$I$4,'Final Project Dataset'!$B$2:$B$251,"<="&$I$5) -> 0
A8: Tablet | B8: =SUMIFS('Final Project Dataset'!$F$2:$F$251,'Final Project Dataset'!$C$2:$C$251,$A8,'Final Project Dataset'!$G$2:$G$251,$I$2,'Final Project Dataset'!$C$2:$C$251,$I$3,'Final Project Dataset'!$B$2:$B$251,">="&$I$4,'Final Project Dataset'!$B$2:$B$251,"<="&$I$5) -> 0 | C8: =SUMIFS('Final Project Dataset'!$H$2:$H$251,'Final Project Dataset'!$C$2:$C$251,$A8,'Final Project Dataset'!$G$2:$G$251,$I$2,'Final Project Dataset'!$C$2:$C$251,$I$3,'Final Project Dataset'!$B$2:$B$251,">="&$I$4,'Final Project Dataset'!$B$2:$B$251,"<="&$I$5) -> 0 | D8: =COUNTIFS('Final Project Dataset'!$C$2:$C$251,$A8,'Final Project Dataset'!$G$2:$G$251,$I$2,'Final Project Dataset'!$C$2:$C$251,$I$3,'Final Project Dataset'!$B$2:$B$251,">="&$I$4,'Final Project Dataset'!$B$2:$B$251,"<="&$I$5) -> 0 | E8: =SUMIFS('Final Project Dataset'!$D$2:$D$251,'Final Project Dataset'!$C$2:$C$251,$A8,'Final Project Dataset'!$G$2:$G$251,$I$2,'Final Project Dataset'!$C$2:$C$251,$I$3,'Final Project Dataset'!$B$2:$B$251,">="&$I$4,'Final Project Dataset'!$B$2:$B$251,"<="&$I$5) -> 0
A9: Smartwatch | B9: =SUMIFS('Final Project Dataset'!$F$2:$F$251,'Final Project Dataset'!$C$2:$C$251,$A9,'Final Project Dataset'!$G$2:$G$251,$I$2,'Final Project Dataset'!$C$2:$C$251,$I$3,'Final Project Dataset'!$B$2:$B$251,">="&$I$4,'Final Project Dataset'!$B$2:$B$251,"<="&$I$5) -> 89673 | C9: =SUMIFS('Final Project Dataset'!$H$2:$H$251,'Final Project Dataset'!$C$2:$C$251,$A9,'Final Project Dataset'!$G$2:$G$251,$I$2,'Final Project Dataset'!$C$2:$C$251,$I$3,'Final Project Dataset'!$B$2:$B$251,">="&$I$4,'Final Project Dataset'!$B$2:$B$251,"<="&$I$5) -> 15915.68 | D9: =COUNTIFS('Final Project Dataset'!$C$2:$C$251,$A9,'Final Project Dataset'!$G$2:$G$251,$I$2,'Final Project Dataset'!$C$2:$C$251,$I$3,'Final Project Dataset'!$B$2:$B$251,">="&$I$4,'Final Project Dataset'!$B$2:$B$251,"<="&$I$5) -> 3 | E9: =SUMIFS('Final Project Dataset'!$D$2:$D$251,'Final Project Dataset'!$C$2:$C$251,$A9,'Final Project Dataset'!$G$2:$G$251,$I$2,'Final Project Dataset'!$C$2:$C$251,$I$3,'Final Project Dataset'!$B$2:$B$251,">="&$I$4,'Final Project Dataset'!$B$2:$B$251,"<="&$I$5) -> 11
A10: Printer | B10: =SUMIFS('Final Project Dataset'!$F$2:$F$251,'Final Project Dataset'!$C$2:$C$251,$A10,'Final Project Dataset'!$G$2:$G$251,$I$2,'Final Project Dataset'!$C$2:$C$251,$I$3,'Final Project Dataset'!$B$2:$B$251,">="&$I$4,'Final Project Dataset'!$B$2:$B$251,"<="&$I$5) -> 0 | C10: =SUMIFS('Final Project Dataset'!$H$2:$H$251,'Final Project Dataset'!$C$2:$C$251,$A10,'Final Project Dataset'!$G$2:$G$251,$I$2,'Final Project Dataset'!$C$2:$C$251,$I$3,'Final Project Dataset'!$B$2:$B$251,">="&$I$4,'Final Project Dataset'!$B$2:$B$251,"<="&$I$5) -> 0 | D10: =COUNTIFS('Final Project Dataset'!$C$2:$C$251,$A10,'Final Project Dataset'!$G$2:$G$251,$I$2,'Final Project Dataset'!$C$2:$C$251,$I$3,'Final Project Dataset'!$B$2:$B$251,">="&$I$4,'Final Project Dataset'!$B$2:$B$251,"<="&$I$5) -> 0 | E10: =SUMIFS('Final Project Dataset'!$D$2:$D$251,'Final Project Dataset'!$C$2:$C$251,$A10,'Final Project Dataset'!$G$2:$G$251,$I$2,'Final Project Dataset'!$C$2:$C$251,$I$3,'Final Project Dataset'!$B$2:$B$251,">="&$I$4,'Final Project Dataset'!$B$2:$B$251,"<="&$I$5) -> 0
A11: Headphones | B11: =SUMIFS('Final Project Dataset'!$F$2:$F$251,'Final Project Dataset'!$C$2:$C$251,$A11,'Final Project Dataset'!$G$2:$G$251,$I$2,'Final Project Dataset'!$C$2:$C$251,$I$3,'Final Project Dataset'!$B$2:$B$251,">="&$I$4,'Final Project Dataset'!$B$2:$B$251,"<="&$I$5) -> 0 | C11: =SUMIFS('Final Project Dataset'!$H$2:$H$251,'Final Project Dataset'!$C$2:$C$251,$A11,'Final Project Dataset'!$G$2:$G$251,$I$2,'Final Project Dataset'!$C$2:$C$251,$I$3,'Final Project Dataset'!$B$2:$B$251,">="&$I$4,'Final Project Dataset'!$B$2:$B$251,"<="&$I$5) -> 0 | D11: =COUNTIFS('Final Project Dataset'!$C$2:$C$251,$A11,'Final Project Dataset'!$G$2:$G$251,$I$2,'Final Project Dataset'!$C$2:$C$251,$I$3,'Final Project Dataset'!$B$2:$B$251,">="&$I$4,'Final Project Dataset'!$B$2:$B$251,"<="&$I$5) -> 0 | E11: =SUMIFS('Final Project Dataset'!$D$2:$D$251,'Final Project Dataset'!$C$2:$C$251,$A11,'Final Project Dataset'!$G$2:$G$251,$I$2,'Final Project Dataset'!$C$2:$C$251,$I$3,'Final Project Dataset'!$B$2:$B$251,">="&$I$4,'Final Project Dataset'!$B$2:$B$251,"<="&$I$5) -> 0
A12: Webcam | B12: =SUMIFS('Final Project Dataset'!$F$2:$F$251,'Final Project Dataset'!$C$2:$C$251,$A12,'Final Project Dataset'!$G$2:$G$251,$I$2,'Final Project Dataset'!$C$2:$C$251,$I$3,'Final Project Dataset'!$B$2:$B$251,">="&$I$4,'Final Project Dataset'!$B$2:$B$251,"<="&$I$5) -> 0 | C12: =SUMIFS('Final Project Dataset'!$H$2:$H$251,'Final Project Dataset'!$C$2:$C$251,$A12,'Final Project Dataset'!$G$2:$G$251,$I$2,'Final Project Dataset'!$C$2:$C$251,$I$3,'Final Project Dataset'!$B$2:$B$251,">="&$I$4,'Final Project Dataset'!$B$2:$B$251,"<="&$I$5) -> 0 | D12: =COUNTIFS('Final Project Dataset'!$C$2:$C$251,$A12,'Final Project Dataset'!$G$2:$G$251,$I$2,'Final Project Dataset'!$C$2:$C$251,$I$3,'Final Project Dataset'!$B$2:$B$251,">="&$I$4,'Final Project Dataset'!$B$2:$B$251,"<="&$I$5) -> 0 | E12: =SUMIFS('Final Project Dataset'!$D$2:$D$251,'Final Project Dataset'!$C$2:$C$251,$A12,'Final Project Dataset'!$G$2:$G$251,$I$2,'Final Project Dataset'!$C$2:$C$251,$I$3,'Final Project Dataset'!$B$2:$B$251,">="&$I$4,'Final Project Dataset'!$B$2:$B$251,"<="&$I$5) -> 0
A13: Keyboard | B13: =SUMIFS('Final Project Dataset'!$F$2:$F$251,'Final Project Dataset'!$C$2:$C$251,$A13,'Final Project Dataset'!$G$2:$G$251,$I$2,'Final Project Dataset'!$C$2:$C$251,$I$3,'Final Project Dataset'!$B$2:$B$251,">="&$I$4,'Final Project Dataset'!$B$2:$B$251,"<="&$I$5) -> 0 | C13: =SUMIFS('Final Project Dataset'!$H$2:$H$251,'Final Project Dataset'!$C$2:$C$251,$A13,'Final Project Dataset'!$G$2:$G$251,$I$2,'Final Project Dataset'!$C$2:$C$251,$I$3,'Final Project Dataset'!$B$2:$B$251,">="&$I$4,'Final Project Dataset'!$B$2:$B$251,"<="&$I$5) -> 0 | D13: =COUNTIFS('Final Project Dataset'!$C$2:$C$251,$A13,'Final Project Dataset'!$G$2:$G$251,$I$2,'Final Project Dataset'!$C$2:$C$251,$I$3,'Final Project Dataset'!$B$2:$B$251,">="&$I$4,'Final Project Dataset'!$B$2:$B$251,"<="&$I$5) -> 0 | E13: =SUMIFS('Final Project Dataset'!$D$2:$D$251,'Final Project Dataset'!$C$2:$C$251,$A13,'Final Project Dataset'!$G$2:$G$251,$I$2,'Final Project Dataset'!$C$2:$C$251,$I$3,'Final Project Dataset'!$B$2:$B$251,">="&$I$4,'Final Project Dataset'!$B$2:$B$251,"<="&$I$5) -> 0
A14: Mouse | B14: =SUMIFS('Final Project Dataset'!$F$2:$F$251,'Final Project Dataset'!$C$2:$C$251,$A14,'Final Project Dataset'!$G$2:$G$251,$I$2,'Final Project Dataset'!$C$2:$C$251,$I$3,'Final Project Dataset'!$B$2:$B$251,">="&$I$4,'Final Project Dataset'!$B$2:$B$251,"<="&$I$5) -> 0 | C14: =SUMIFS('Final Project Dataset'!$H$2:$H$251,'Final Project Dataset'!$C$2:$C$251,$A14,'Final Project Dataset'!$G$2:$G$251,$I$2,'Final Project Dataset'!$C$2:$C$251,$I$3,'Final Project Dataset'!$B$2:$B$251,">="&$I$4,'Final Project Dataset'!$B$2:$B$251,"<="&$I$5) -> 0 | D14: =COUNTIFS('Final Project Dataset'!$C$2:$C$251,$A14,'Final Project Dataset'!$G$2:$G$251,$I$2,'Final Project Dataset'!$C$2:$C$251,$I$3,'Final Project Dataset'!$B$2:$B$251,">="&$I$4,'Final Project Dataset'!$B$2:$B$251,"<="&$I$5) -> 0 | E14: =SUMIFS('Final Project Dataset'!$D$2:$D$251,'Final Project Dataset'!$C$2:$C$251,$A14,'Final Project Dataset'!$G$2:$G$251,$I$2,'Final Project Dataset'!$C$2:$C$251,$I$3,'Final Project Dataset'!$B$2:$B$251,">="&$I$4,'Final Project Dataset'!$B$2:$B$251,"<="&$I$5) -> 0
A15: Grand Total | B15: =SUM(B5:B14) -> 89673 | C15: =SUM(C5:C14) -> 15915.68 | D15: =SUM(D5:D14) -> 3 | E15: =SUM(E5:E14) -> 11
A17: By Region
A18: Region | B18: Sales (₹) | C18: Profit (₹) | D18: Transactions | E18: Units
A19: North | B19: =SUMIFS('Final Project Dataset'!$F$2:$F$251,'Final Project Dataset'!$G$2:$G$251,$A19,'Final Project Dataset'!$G$2:$G$251,$I$2,'Final Project Dataset'!$C$2:$C$251,$I$3,'Final Project Dataset'!$B$2:$B$251,">="&$I$4,'Final Project Dataset'!$B$2:$B$251,"<="&$I$5) -> 0 | C19: =SUMIFS('Final Project Dataset'!$H$2:$H$251,'Final Project Dataset'!$G$2:$G$251,$A19,'Final Project Dataset'!$G$2:$G$251,$I$2,'Final Project Dataset'!$C$2:$C$251,$I$3,'Final Project Dataset'!$B$2:$B$251,">="&$I$4,'Final Project Dataset'!$B$2:$B$251,"<="&$I$5) -> 0 | D19: =COUNTIFS('Final Project Dataset'!$G$2:$G$251,$A19,'Final Project Dataset'!$G$2:$G$251,$I$2,'Final Project Dataset'!$C$2:$C$251,$I$3,'Final Project Dataset'!$B$2:$B$251,">="&$I$4,'Final Project Dataset'!$B$2:$B$251,"<="&$I$5) -> 0 | E19: =SUMIFS('Final Project Dataset'!$D$2:$D$251,'Final Project Dataset'!$G$2:$G$251,$A19,'Final Project Dataset'!$G$2:$G$251,$I$2,'Final Project Dataset'!$C$2:$C$251,$I$3,'Final Project Dataset'!$B$2:$B$251,">="&$I$4,'Final Project Dataset'!$B$2:$B$251,"<="&$I$5) -> 0
A20: South | B20: =SUMIFS('Final Project Dataset'!$F$2:$F$251,'Final Project Dataset'!$G$2:$G$251,$A20,'Final Project Dataset'!$G$2:$G$251,$I$2,'Final Project Dataset'!$C$2:$C$251,$I$3,'Final Project Dataset'!$B$2:$B$251,">="&$I$4,'Final Project Dataset'!$B$2:$B$251,"<="&$I$5) -> 89673 | C20: =SUMIFS('Final Project Dataset'!$H$2:$H$251,'Final Project Dataset'!$G$2:$G$251,$A20,'Final Project Dataset'!$G$2:$G$251,$I$2,'Final Project Dataset'!$C$2:$C$251,$I$3,'Final Project Dataset'!$B$2:$B$251,">="&$I$4,'Final Project Dataset'!$B$2:$B$251,"<="&$I$5) -> 15915.68 | D20: =COUNTIFS('Final Project Dataset'!$G$2:$G$251,$A20,'Final Project Dataset'!$G$2:$G$251,$I$2,'Final Project Dataset'!$C$2:$C$251,$I$3,'Final Project Dataset'!$B$2:$B$251,">="&$I$4,'Final Project Dataset'!$B$2:$B$251,"<="&$I$5) -> 3 | E20: =SUMIFS('Final Project Dataset'!$D$2:$D$251,'Final Project Dataset'!$G$2:$G$251,$A20,'Final Project Dataset'!$G$2:$G$251,$I$2,'Final Project Dataset'!$C$2:$C$251,$I$3,'Final Project Dataset'!$B$2:$B$251,">="&$I$4,'Final Project Dataset'!$B$2:$B$251,"<="&$I$5) -> 11
A21: East | B21: =SUMIFS('Final Project Dataset'!$F$2:$F$251,'Final Project Dataset'!$G$2:$G$251,$A21,'Final Project Dataset'!$G$2:$G$251,$I$2,'Final Project Dataset'!$C$2:$C$251,$I$3,'Final Project Dataset'!$B$2:$B$251,">="&$I$4,'Final Project Dataset'!$B$2:$B$251,"<="&$I$5) -> 0 | C21: =SUMIFS('Final Project Dataset'!$H$2:$H$251,'Final Project Dataset'!$G$2:$G$251,$A21,'Final Project Dataset'!$G$2:$G$251,$I$2,'Final Project Dataset'!$C$2:$C$251,$I$3,'Final Project Dataset'!$B$2:$B$251,">="&$I$4,'Final Project Dataset'!$B$2:$B$251,"<="&$I$5) -> 0 | D21: =COUNTIFS('Final Project Dataset'!$G$2:$G$251,$A21,'Final Project Dataset'!$G$2:$G$251,$I$2,'Final Project Dataset'!$C$2:$C$251,$I$3,'Final Project Dataset'!$B$2:$B$251,">="&$I$4,'Final Project Dataset'!$B$2:$B$251,"<="&$I$5) -> 0 | E21: =SUMIFS('Final Project Dataset'!$D$2:$D$251,'Final Project Dataset'!$G$2:$G$251,$A21,'Final Project Dataset'!$G$2:$G$251,$I$2,'Final Project Dataset'!$C$2:$C$251,$I$3,'Final Project Dataset'!$B$2:$B$251,">="&$I$4,'Final Project Dataset'!$B$2:$B$251,"<="&$I$5) -> 0
A22: West | B22: =SUMIFS('Final Project Dataset'!$F$2:$F$251,'Final Project Dataset'!$G$2:$G$251,$A22,'Final Project Dataset'!$G$2:$G$251,$I$2,'Final Project Dataset'!$C$2:$C$251,$I$3,'Final Project Dataset'!$B$2:$B$251,">="&$I$4,'Final Project Dataset'!$B$2:$B$251,"<="&$I$5) -> 0 | C22: =SUMIFS('Final Project Dataset'!$H$2:$H$251,'Final Project Dataset'!$G$2:$G$251,$A22,'Final Project Dataset'!$G$2:$G$251,$I$2,'Final Project Dataset'!$C$2:$C$251,$I$3,'Final Project Dataset'!$B$2:$B$251,">="&$I$4,'Final Project Dataset'!$B$2:$B$251,"<="&$I$5) -> 0 | D22: =COUNTIFS('Final Project Dataset'!$G$2:$G$251,$A22,'Final Project Dataset'!$G$2:$G$251,$I$2,'Final Project Dataset'!$C$2:$C$251,$I$3,'Final Project Dataset'!$B$2:$B$251,">="&$I$4,'Final Project Dataset'!$B$2:$B$251,"<="&$I$5) -> 0 | E22: =SUMIFS('Final Project Dataset'!$D$2:$D$251,'Final Project Dataset'!$G$2:$G$251,$A22,'Final Project Dataset'!$G$2:$G$251,$I$2,'Final Project Dataset'!$C$2:$C$251,$I$3,'Final Project Dataset'!$B$2:$B$251,">="&$I$4,'Final Project Dataset'!$B$2:$B$251,"<="&$I$5) -> 0
A23: Central | B23: =SUMIFS('Final Project Dataset'!$F$2:$F$251,'Final Project Dataset'!$G$2:$G$251,$A23,'Final Project Dataset'!$G$2:$G$251,$I$2,'Final Project Dataset'!$C$2:$C$251,$I$3,'Final Project Dataset'!$B$2:$B$251,">="&$I$4,'Final Project Dataset'!$B$2:$B$251,"<="&$I$5) -> 0 | C23: =SUMIFS('Final Project Dataset'!$H$2:$H$251,'Final Project Dataset'!$G$2:$G$251,$A23,'Final Project Dataset'!$G$2:$G$251,$I$2,'Final Project Dataset'!$C$2:$C$251,$I$3,'Final Project Dataset'!$B$2:$B$251,">="&$I$4,'Final Project Dataset'!$B$2:$B$251,"<="&$I$5) -> 0 | D23: =COUNTIFS('Final Project Dataset'!$G$2:$G$251,$A23,'Final Project Dataset'!$G$2:$G$251,$I$2,'Final Project Dataset'!$C$2:$C$251,$I$3,'Final Project Dataset'!$B$2:$B$251,">="&$I$4,'Final Project Dataset'!$B$2:$B$251,"<="&$I$5) -> 0 | E23: =SUMIFS('Final Project Dataset'!$D$2:$D$251,'Final Project Dataset'!$G$2:$G$251,$A23,'Final Project Dataset'!$G$2:$G$251,$I$2,'Final Project Dataset'!$C$2:$C$251,$I$3,'Final Project Dataset'!$B$2:$B$251,">="&$I$4,'Final Project Dataset'!$B$2:$B$251,"<="&$I$5) -> 0
A24: Grand Total | B24: =SUM(B19:B23) -> 89673 | C24: =SUM(C19:C23) -> 15915.68 | D24: =SUM(D19:D23) -> 3 | E24: =SUM(E19:E23) -> 11
A26: By Payment Method
A27: Payment Method | B27: Sales (₹) | C27: Profit (₹) | D27: Transactions | E27: Units
A28: Credit Card | B28: =SUMIFS('Final Project Dataset'!$F$2:$F$251,'Final Project Dataset'!$J$2:$J$251,$A28,'Final Project Dataset'!$G$2:$G$251,$I$2,'Final Project Dataset'!$C$2:$C$251,$I$3,'Final Project Dataset'!$B$2:$B$251,">="&$I$4,'Final Project Dataset'!$B$2:$B$251,"<="&$I$5) -> 31036 | C28: =SUMIFS('Final Project Dataset'!$H$2:$H$251,'Final Project Dataset'!$J$2:$J$251,$A28,'Final Project Dataset'!$G$2:$G$251,$I$2,'Final Project Dataset'!$C$2:$C$251,$I$3,'Final Project Dataset'!$B$2:$B$251,">="&$I$4,'Final Project Dataset'!$B$2:$B$251,"<="&$I$5) -> 6292.17 | D28: =COUNTIFS('Final Project Dataset'!$J$2:$J$251,$A28,'Final Project Dataset'!$G$2:$G$251,$I$2,'Final Project Dataset'!$C$2:$C$251,$I$3,'Final Project Dataset'!$B$2:$B$251,">="&$I$4,'Final Project Dataset'!$B$2:$B$251,"<="&$I$5) -> 1 | E28: =SUMIFS('Final Project Dataset'!$D$2:$D$251,'Final Project Dataset'!$J$2:$J$251,$A28,'Final Project Dataset'!$G$2:$G$251,$I$2,'Final Project Dataset'!$C$2:$C$251,$I$3,'Final Project Dataset'!$B$2:$B$251,">="&$I$4,'Final Project Dataset'!$B$2:$B$251,"<="&$I$5) -> 4
A29: Debit Card | B29: =SUMIFS('Final Project Dataset'!$F$2:$F$251,'Final Project Dataset'!$J$2:$J$251,$A29,'Final Project Dataset'!$G$2:$G$251,$I$2,'Final Project Dataset'!$C$2:$C$251,$I$3,'Final Project Dataset'!$B$2:$B$251,">="&$I$4,'Final Project Dataset'!$B$2:$B$251,"<="&$I$5) -> 0 | C29: =SUMIFS('Final Project Dataset'!$H$2:$H$251,'Final Project Dataset'!$J$2:$J$251,$A29,'Final Project Dataset'!$G$2:$G$251,$I$2,'Final Project Dataset'!$C$2:$C$251,$I$3,'Final Project Dataset'!$B$2:$B$251,">="&$I$4,'Final Project Dataset'!$B$2:$B$251,"<="&$I$5) -> 0 | D29: =COUNTIFS('Final Project Dataset'!$J$2:$J$251,$A29,'Final Project Dataset'!$G$2:$G$251,$I$2,'Final Project Dataset'!$C$2:$C$251,$I$3,'Final Project Dataset'!$B$2:$B$251,">="&$I$4,'Final Project Dataset'!$B$2:$B$251,"<="&$I$5) -> 0 | E29: =SUMIFS('Final Project Dataset'!$D$2:$D$251,'Final Project Dataset'!$J$2:$J$251,$A29,'Final Project Dataset'!$G$2:$G$251,$I$2,'Final Project Dataset'!$C$2:$C$251,$I$3,'Final Project Dataset'!$B$2:$B$251,">="&$I$4,'Final Project Dataset'!$B$2:$B$251,"<="&$I$5) -> 0
A30: UPI | B30: =SUMIFS('Final Project Dataset'!$F$2:$F$251,'Final Project Dataset'!$J$2:$J$251,$A30,'Final Project Dataset'!$G$2:$G$251,$I$2,'Final Project Dataset'!$C$2:$C$251,$I$3,'Final Project Dataset'!$B$2:$B$251,">="&$I$4,'Final Project Dataset'!$B$2:$B$251,"<="&$I$5) -> 43305 | C30: =SUMIFS('Final Project Dataset'!$H$2:$H$251,'Final Project Dataset'!$J$2:$J$251,$A30,'Final Project Dataset'!$G$2:$G$251,$I$2,'Final Project Dataset'!$C$2:$C$251,$I$3,'Final Project Dataset'!$B$2:$B$251,">="&$I$4,'Final Project Dataset'!$B$2:$B$251,"<="&$I$5) -> 7627.95 | D30: =COUNTIFS('Final Project Dataset'!$J$2:$J$251,$A30,'Final Project Dataset'!$G$2:$G$251,$I$2,'Final Project Dataset'!$C$2:$C$251,$I$3,'Final Project Dataset'!$B$2:$B$251,">="&$I$4,'Final Project Dataset'!$B$2:$B$251,"<="&$I$5) -> 1 | E30: =SUMIFS('Final Project Dataset'!$D$2:$D$251,'Final Project Dataset'!$J$2:$J$251,$A30,'Final Project Dataset'!$G$2:$G$251,$I$2,'Final Project Dataset'!$C$2:$C$251,$I$3,'Final Project Dataset'!$B$2:$B$251,">="&$I$4,'Final Project Dataset'!$B$2:$B$251,"<="&$I$5) -> 5
A31: Cash | B31: =SUMIFS('Final Project Dataset'!$F$2:$F$251,'Final Project Dataset'!$J$2:$J$251,$A31,'Final Project Dataset'!$G$2:$G$251,$I$2,'Final Project Dataset'!$C$2:$C$251,$I$3,'Final Project Dataset'!$B$2:$B$251,">="&$I$4,'Final Project Dataset'!$B$2:$B$251,"<="&$I$5) -> 15332 | C31: =SUMIFS('Final Project Dataset'!$H$2:$H$251,'Final Project Dataset'!$J$2:$J$251,$A31,'Final Project Dataset'!$G$2:$G$251,$I$2,'Final Project Dataset'!$C$2:$C$251,$I$3,'Final Project Dataset'!$B$2:$B$251,">="&$I$4,'Final Project Dataset'!$B$2:$B$251,"<="&$I$5) -> 1995.56 | D31: =COUNTIFS('Final Project Dataset'!$J$2:$J$251,$A31,'Final Project Dataset'!$G$2:$G$251,$I$2,'Final Project Dataset'!$C$2:$C$251,$I$3,'Final Project Dataset'!$B$2:$B$251,">="&$I$4,'Final Project Dataset'!$B$2:$B$251,"<="&$I$5) -> 1 | E31: =SUMIFS('Final Project Dataset'!$D$2:$D$251,'Final Project Dataset'!$J$2:$J$251,$A31,'Final Project Dataset'!$G$2:$G$251,$I$2,'Final Project Dataset'!$C$2:$C$251,$I$3,'Final Project Dataset'!$B$2:$B$251,">="&$I$4,'Final Project Dataset'!$B$2:$B$251,"<="&$I$5) -> 2
A32: Net Banking | B32: =SUMIFS('Final Project Dataset'!$F$2:$F$251,'Final Project Dataset'!$J$2:$J$251,$A32,'Final Project Dataset'!$G$2:$G$251,$I$2,'Final Project Dataset'!$C$2:$C$251,$I$3,'Final Project Dataset'!$B$2:$B$251,">="&$I$4,'Final Project Dataset'!$B$2:$B$251,"<="&$I$5) -> 0 | C32: =SUMIFS('Final Project Dataset'!$H$2:$H$251,'Final Project Dataset'!$J$2:$J$251,$A32,'Final Project Dataset'!$G$2:$G$251,$I$2,'Final Project Dataset'!$C$2:$C$251,$I$3,'Final Project Dataset'!$B$2:$B$251,">="&$I$4,'Final Project Dataset'!$B$2:$B$251,"<="&$I$5) -> 0 | D32: =COUNTIFS('Final Project Dataset'!$J$2:$J$251,$A32,'Final Project Dataset'!$G$2:$G$251,$I$2,'Final Project Dataset'!$C$2:$C$251,$I$3,'Final Project Dataset'!$B$2:$B$251,">="&$I$4,'Final Project Dataset'!$B$2:$B$251,"<="&$I$5) -> 0 | E32: =SUMIFS('Final Project Dataset'!$D$2:$D$251,'Final Project Dataset'!$J$2:$J$251,$A32,'Final Project Dataset'!$G$2:$G$251,$I$2,'Final Project Dataset'!$C$2:$C$251,$I$3,'Final Project Dataset'!$B$2:$B$251,">="&$I$4,'Final Project Dataset'!$B$2:$B$251,"<="&$I$5) -> 0
A33: Grand Total | B33: =SUM(B28:B32) -> 89673 | C33: =SUM(C28:C32) -> 15915.68 | D33: =SUM(D28:D32) -> 3 | E33: =SUM(E28:E32) -> 11
A35: By Month (timeline)
A36: Month | B36: Sales (₹) | C36: Profit (₹) | D36: Transactions | E36: Units | F36: Label
A37: =DATE(2025,1,1) -> 45658 | B37: =SUMIFS('Final Project Dataset'!$F$2:$F$251,'Final Project Dataset'!$G$2:$G$251,$I$2,'Final Project Dataset'!$C$2:$C$251,$I$3,'Final Project Dataset'!$B$2:$B$251,">="&MAX($A37,$I$4),'Final Project Dataset'!$B$2:$B$251,"<="&MIN(EOMONTH($A37,0),$I$5)) -> 0 | C37: =SUMIFS('Final Project Dataset'!$H$2:$H$251,'Final Project Dataset'!$G$2:$G$251,$I$2,'Final Project Dataset'!$C$2:$C$251,$I$3,'Final Project Dataset'!$B$2:$B$251,">="&MAX($A37,$I$4),'Final Project Dataset'!$B$2:$B$251,"<="&MIN(EOMONTH($A37,0),$I$5)) -> 0 | D37: =COUNTIFS('Final Project Dataset'!$G$2:$G$251,$I$2,'Final Project Dataset'!$C$2:$C$251,$I$3,'Final Project Dataset'!$B$2:$B$251,">="&MAX($A37,$I$4),'Final Project Dataset'!$B$2:$B$251,"<="&MIN(EOMONTH($A37,0),$I$5)) -> 0 | E37: =SUMIFS('Final Project Dataset'!$D$2:$D$251,'Final Project Dataset'!$G$2:$G$251,$I$2,'Final Project Dataset'!$C$2:$C$251,$I$3,'Final Project Dataset'!$B$2:$B$251,">="&MAX($A37,$I$4),'Final Project Dataset'!$B$2:$B$251,"<="&MIN(EOMONTH($A37,0),$I$5)) -> 0 | F37: =TEXT(A37,"mmm yy") -> Jan 25
A38: =EDATE(A37,1) -> 45689 | B38: =SUMIFS('Final Project Dataset'!$F$2:$F$251,'Final Project Dataset'!$G$2:$G$251,$I$2,'Final Project Dataset'!$C$2:$C$251,$I$3,'Final Project Dataset'!$B$2:$B$251,">="&MAX($A38,$I$4),'Final Project Dataset'!$B$2:$B$251,"<="&MIN(EOMONTH($A38,0),$I$5)) -> 0 | C38: =SUMIFS('Final Project Dataset'!$H$2:$H$251,'Final Project Dataset'!$G$2:$G$251,$I$2,'Final Project Dataset'!$C$2:$C$251,$I$3,'Final Project Dataset'!$B$2:$B$251,">="&MAX($A38,$I$4),'Final Project Dataset'!$B$2:$B$251,"<="&MIN(EOMONTH($A38,0),$I$5)) -> 0 | D38: =COUNTIFS('Final Project Dataset'!$G$2:$G$251,$I$2,'Final Project Dataset'!$C$2:$C$251,$I$3,'Final Project Dataset'!$B$2:$B$251,">="&MAX($A38,$I$4),'Final Project Dataset'!$B$2:$B$251,"<="&MIN(EOMONTH($A38,0),$I$5)) -> 0 | E38: =SUMIFS('Final Project Dataset'!$D$2:$D$251,'Final Project Dataset'!$G$2:$G$251,$I$2,'Final Project Dataset'!$C$2:$C$251,$I$3,'Final Project Dataset'!$B$2:$B$251,">="&MAX($A38,$I$4),'Final Project Dataset'!$B$2:$B$251,"<="&MIN(EOMONTH($A38,0),$I$5)) -> 0 | F38: =TEXT(A38,"mmm yy") -> Feb 25
A39: =EDATE(A38,1) -> 45717 | B39: =SUMIFS('Final Project Dataset'!$F$2:$F$251,'Final Project Dataset'!$G$2:$G$251,$I$2,'Final Project Dataset'!$C$2:$C$251,$I$3,'Final Project Dataset'!$B$2:$B$251,">="&MAX($A39,$I$4),'Final Project Dataset'!$B$2:$B$251,"<="&MIN(EOMONTH($A39,0),$I$5)) -> 43305 | C39: =SUMIFS('Final Project Dataset'!$H$2:$H$251,'Final Project Dataset'!$G$2:$G$251,$I$2,'Final Project Dataset'!$C$2:$C$251,$I$3,'Final Project Dataset'!$B$2:$B$251,">="&MAX($A39,$I$4),'Final Project Dataset'!$B$2:$B$251,"<="&MIN(EOMONTH($A39,0),$I$5)) -> 7627.95 | D39: =COUNTIFS('Final Project Dataset'!$G$2:$G$251,$I$2,'Final Project Dataset'!$C$2:$C$251,$I$3,'Final Project Dataset'!$B$2:$B$251,">="&MAX($A39,$I$4),'Final Project Dataset'!$B$2:$B$251,"<="&MIN(EOMONTH($A39,0),$I$5)) -> 1 | E39: =SUMIFS('Final Project Dataset'!$D$2:$D$251,'Final Project Dataset'!$G$2:$G$251,$I$2,'Final Project Dataset'!$C$2:$C$251,$I$3,'Final Project Dataset'!$B$2:$B$251,">="&MAX($A39,$I$4),'Final Project Dataset'!$B$2:$B$251,"<="&MIN(EOMONTH($A39,0),$I$5)) -> 5 | F39: =TEXT(A39,"mmm yy") -> Mar 25
A40: =EDATE(A39,1) -> 45748 | B40: =SUMIFS('Final Project Dataset'!$F$2:$F$251,'Final Project Dataset'!$G$2:$G$251,$I$2,'Final Project Dataset'!$C$2:$C$251,$I$3,'Final Project Dataset'!$B$2:$B$251,">="&MAX($A40,$I$4),'Final Project Dataset'!$B$2:$B$251,"<="&MIN(EOMONTH($A40,0),$I$5)) -> 0 | C40: =SUMIFS('Final Project Dataset'!$H$2:$H$251,'Final Project Dataset'!$G$2:$G$251,$I$2,'Final Project Dataset'!$C$2:$C$251,$I$3,'Final Project Dataset'!$B$2:$B$251,">="&MAX($A40,$I$4),'Final Project Dataset'!$B$2:$B$251,"<="&MIN(EOMONTH($A40,0),$I$5)) -> 0 | D40: =COUNTIFS('Final Project Dataset'!$G$2:$G$251,$I$2,'Final Project Dataset'!$C$2:$C$251,$I$3,'Final Project Dataset'!$B$2:$B$251,">="&MAX($A40,$I$4),'Final Project Dataset'!$B$2:$B$251,"<="&MIN(EOMONTH($A40,0),$I$5)) -> 0 | E40: =SUMIFS('Final Project Dataset'!$D$2:$D$251,'Final Project Dataset'!$G$2:$G$251,$I$2,'Final Project Dataset'!$C$2:$C$251,$I$3,'Final Project Dataset'!$B$2:$B$251,">="&MAX($A40,$I$4),'Final Project Dataset'!$B$2:$B$251,"<="&MIN(EOMONTH($A40,0),$I$5)) -> 0 | F40: =TEXT(A40,"mmm yy") -> Apr 25
A41: =EDATE(A40,1) -> 45778 | B41: =SUMIFS('Final Project Dataset'!$F$2:$F$251,'Final Project Dataset'!$G$2:$G$251,$I$2,'Final Project Dataset'!$C$2:$C$251,$I$3,'Final Project Dataset'!$B$2:$B$251,">="&MAX($A41,$I$4),'Final Project Dataset'!$B$2:$B$251,"<="&MIN(EOMONTH($A41,0),$I$5)) -> 0 | C41: =SUMIFS('Final Project Dataset'!$H$2:$H$251,'Final Project Dataset'!$G$2:$G$251,$I$2,'Final Project Dataset'!$C$2:$C$251,$I$3,'Final Project Dataset'!$B$2:$B$251,">="&MAX($A41,$I$4),'Final Project Dataset'!$B$2:$B$251,"<="&MIN(EOMONTH($A41,0),$I$5)) -> 0 | D41: =COUNTIFS('Final Project Dataset'!$G$2:$G$251,$I$2,'Final Project Dataset'!$C$2:$C$251,$I$3,'Final Project Dataset'!$B$2:$B$251,">="&MAX($A41,$I$4),'Final Project Dataset'!$B$2:$B$251,"<="&MIN(EOMONTH($A41,0),$I$5)) -> 0 | E41: =SUMIFS('Final Project Dataset'!$D$2:$D$251,'Final Project Dataset'!$G$2:$G$251,$I$2,'Final Project Dataset'!$C$2:$C$251,$I$3,'Final Project Dataset'!$B$2:$B$251,">="&MAX($A41,$I$4),'Final Project Dataset'!$B$2:$B$251,"<="&MIN(EOMONTH($A41,0),$I$5)) -> 0 | F41: =TEXT(A41,"mmm yy") -> May 25
A42: =EDATE(A41,1) -> 45809 | B42: =SUMIFS('Final Project Dataset'!$F$2:$F$251,'Final Project Dataset'!$G$2:$G$251,$I$2,'Final Project Dataset'!$C$2:$C$251,$I$3,'Final Project Dataset'!$B$2:$B$251,">="&MAX($A42,$I$4),'Final Project Dataset'!$B$2:$B$251,"<="&MIN(EOMONTH($A42,0),$I$5)) -> 15332 | C42: =SUMIFS('Final Project Dataset'!$H$2:$H$251,'Final Project Dataset'!$G$2:$G$251,$I$2,'Final Project Dataset'!$C$2:$C$251,$I$3,'Final Project Dataset'!$B$2:$B$251,">="&MAX($A42,$I$4),'Final Project Dataset'!$B$2:$B$251,"<="&MIN(EOMONTH($A42,0),$I$5)) -> 1995.56 | D42: =COUNTIFS('Final Project Dataset'!$G$2:$G$251,$I$2,'Final Project Dataset'!$C$2:$C$251,$I$3,'Final Project Dataset'!$B$2:$B$251,">="&MAX($A42,$I$4),'Final Project Dataset'!$B$2:$B$251,"<="&MIN(EOMONTH($A42,0),$I$5)) -> 1 | E42: =SUMIFS('Final Project Dataset'!$D$2:$D$251,'Final Project Dataset'!$G$2:$G$251,$I$2,'Final Project Dataset'!$C$2:$C$251,$I$3,'Final Project Dataset'!$B$2:$B$251,">="&MAX($A42,$I$4),'Final Project Dataset'!$B$2:$B$251,"<="&MIN(EOMONTH($A42,0),$I$5)) -> 2 | F42: =TEXT(A42,"mmm yy") -> Jun 25
A43: =EDATE(A42,1) -> 45839 | B43: =SUMIFS('Final Project Dataset'!$F$2:$F$251,'Final Project Dataset'!$G$2:$G$251,$I$2,'Final Project Dataset'!$C$2:$C$251,$I$3,'Final Project Dataset'!$B$2:$B$251,">="&MAX($A43,$I$4),'Final Project Dataset'!$B$2:$B$251,"<="&MIN(EOMONTH($A43,0),$I$5)) -> 0 | C43: =SUMIFS('Final Project Dataset'!$H$2:$H$251,'Final Project Dataset'!$G$2:$G$251,$I$2,'Final Project Dataset'!$C$2:$C$251,$I$3,'Final Project Dataset'!$B$2:$B$251,">="&MAX($A43,$I$4),'Final Project Dataset'!$B$2:$B$251,"<="&MIN(EOMONTH($A43,0),$I$5)) -> 0 | D43: =COUNTIFS('Final Project Dataset'!$G$2:$G$251,$I$2,'Final Project Dataset'!$C$2:$C$251,$I$3,'Final Project Dataset'!$B$2:$B$251,">="&MAX($A43,$I$4),'Final Project Dataset'!$B$2:$B$251,"<="&MIN(EOMONTH($A43,0),$I$5)) -> 0 | E43: =SUMIFS('Final Project Dataset'!$D$2:$D$251,'Final Project Dataset'!$G$2:$G$251,$I$2,'Final Project Dataset'!$C$2:$C$251,$I$3,'Final Project Dataset'!$B$2:$B$251,">="&MAX($A43,$I$4),'Final Project Dataset'!$B$2:$B$251,"<="&MIN(EOMONTH($A43,0),$I$5)) -> 0 | F43: =TEXT(A43,"mmm yy") -> Jul 25
A44: =EDATE(A43,1) -> 45870 | B44: =SUMIFS('Final Project Dataset'!$F$2:$F$251,'Final Project Dataset'!$G$2:$G$251,$I$2,'Final Project Dataset'!$C$2:$C$251,$I$3,'Final Project Dataset'!$B$2:$B$251,">="&MAX($A44,$I$4),'Final Project Dataset'!$B$2:$B$251,"<="&MIN(EOMONTH($A44,0),$I$5)) -> 0 | C44: =SUMIFS('Final Project Dataset'!$H$2:$H$251,'Final Project Dataset'!$G$2:$G$251,$I$2,'Final Project Dataset'!$C$2:$C$251,$I$3,'Final Project Dataset'!$B$2:$B$251,">="&MAX($A44,$I$4),'Final Project Dataset'!$B$2:$B$251,"<="&MIN(EOMONTH($A44,0),$I$5)) -> 0 | D44: =COUNTIFS('Final Project Dataset'!$G$2:$G$251,$I$2,'Final Project Dataset'!$C$2:$C$251,$I$3,'Final Project Dataset'!$B$2:$B$251,">="&MAX($A44,$I$4),'Final Project Dataset'!$B$2:$B$251,"<="&MIN(EOMONTH($A44,0),$I$5)) -> 0 | E44: =SUMIFS('Final Project Dataset'!$D$2:$D$251,'Final Project Dataset'!$G$2:$G$251,$I$2,'Final Project Dataset'!$C$2:$C$251,$I$3,'Final Project Dataset'!$B$2:$B$251,">="&MAX($A44,$I$4),'Final Project Dataset'!$B$2:$B$251,"<="&MIN(EOMONTH($A44,0),$I$5)) -> 0 | F44: =TEXT(A44,"mmm yy") -> Aug 25
A45: =EDATE(A44,1) -> 45901 | B45: =SUMIFS('Final Project Dataset'!$F$2:$F$251,'Final Project Dataset'!$G$2:$G$251,$I$2,'Final Project Dataset'!$C$2:$C$251,$I$3,'Final Project Dataset'!$B$2:$B$251,">="&MAX($A45,$I$4),'Final Project Dataset'!$B$2:$B$251,"<="&MIN(EOMONTH($A45,0),$I$5)) -> 0 | C45: =SUMIFS('Final Project Dataset'!$H$2:$H$251,'Final Project Dataset'!$G$2:$G$251,$I$2,'Final Project Dataset'!$C$2:$C$251,$I$3,'Final Project Dataset'!$B$2:$B$251,">="&MAX($A45,$I$4),'Final Project Dataset'!$B$2:$B$251,"<="&MIN(EOMONTH($A45,0),$I$5)) -> 0 | D45: =COUNTIFS('Final Project Dataset'!$G$2:$G$251,$I$2,'Final Project Dataset'!$C$2:$C$251,$I$3,'Final Project Dataset'!$B$2:$B$251,">="&MAX($A45,$I$4),'Final Project Dataset'!$B$2:$B$251,"<="&MIN(EOMONTH($A45,0),$I$5)) -> 0 | E45: =SUMIFS('Final Project Dataset'!$D$2:$D$251,'Final Project Dataset'!$G$2:$G$251,$I$2,'Final Project Dataset'!$C$2:$C$251,$I$3,'Final Project Dataset'!$B$2:$B$251,">="&MAX($A45,$I$4),'Final Project Dataset'!$B$2:$B$251,"<="&MIN(EOMONTH($A45,0),$I$5)) -> 0 | F45: =TEXT(A45,"mmm yy") -> Sep 25
A46: =EDATE(A45,1) -> 45931 | B46: =SUMIFS('Final Project Dataset'!$F$2:$F$251,'Final Project Dataset'!$G$2:$G$251,$I$2,'Final Project Dataset'!$C$2:$C$251,$I$3,'Final Project Dataset'!$B$2:$B$251,">="&MAX($A46,$I$4),'Final Project Dataset'!$B$2:$B$251,"<="&MIN(EOMONTH($A46,0),$I$5)) -> 0 | C46: =SUMIFS('Final Project Dataset'!$H$2:$H$251,'Final Project Dataset'!$G$2:$G$251,$I$2,'Final Project Dataset'!$C$2:$C$251,$I$3,'Final Project Dataset'!$B$2:$B$251,">="&MAX($A46,$I$4),'Final Project Dataset'!$B$2:$B$251,"<="&MIN(EOMONTH($A46,0),$I$5)) -> 0 | D46: =COUNTIFS('Final Project Dataset'!$G$2:$G$251,$I$2,'Final Project Dataset'!$C$2:$C$251,$I$3,'Final Project Dataset'!$B$2:$B$251,">="&MAX($A46,$I$4),'Final Project Dataset'!$B$2:$B$251,"<="&MIN(EOMONTH($A46,0),$I$5)) -> 0 | E46: =SUMIFS('Final Project Dataset'!$D$2:$D$251,'Final Project Dataset'!$G$2:$G$251,$I$2,'Final Project Dataset'!$C$2:$C$251,$I$3,'Final Project Dataset'!$B$2:$B$251,">="&MAX($A46,$I$4),'Final Project Dataset'!$B$2:$B$251,"<="&MIN(EOMONTH($A46,0),$I$5)) -> 0 | F46: =TEXT(A46,"mmm yy") -> Oct 25
A47: =EDATE(A46,1) -> 45962 | B47: =SUMIFS('Final Project Dataset'!$F$2:$F$251,'Final Project Dataset'!$G$2:$G$251,$I$2,'Final Project Dataset'!$C$2:$C$251,$I$3,'Final Project Dataset'!$B$2:$B$251,">="&MAX($A47,$I$4),'Final Project Dataset'!$B$2:$B$251,"<="&MIN(EOMONTH($A47,0),$I$5)) -> 31036 | C47: =SUMIFS('Final Project Dataset'!$H$2:$H$251,'Final Project Dataset'!$G$2:$G$251,$I$2,'Final Project Dataset'!$C$2:$C$251,$I$3,'Final Project Dataset'!$B$2:$B$251,">="&MAX($A47,$I$4),'Final Project Dataset'!$B$2:$B$251,"<="&MIN(EOMONTH($A47,0),$I$5)) -> 6292.17 | D47: =COUNTIFS('Final Project Dataset'!$G$2:$G$251,$I$2,'Final Project Dataset'!$C$2:$C$251,$I$3,'Final Project Dataset'!$B$2:$B$251,">="&MAX($A47,$I$4),'Final Project Dataset'!$B$2:$B$251,"<="&MIN(EOMONTH($A47,0),$I$5)) -> 1 | E47: =SUMIFS('Final Project Dataset'!$D$2:$D$251,'Final Project Dataset'!$G$2:$G$251,$I$2,'Final Project Dataset'!$C$2:$C$251,$I$3,'Final Project Dataset'!$B$2:$B$251,">="&MAX($A47,$I$4),'Final Project Dataset'!$B$2:$B$251,"<="&MIN(EOMONTH($A47,0),$I$5)) -> 4 | F47: =TEXT(A47,"mmm yy") -> Nov 25
A48: =EDATE(A47,1) -> 45992 | B48: =SUMIFS('Final Project Dataset'!$F$2:$F$251,'Final Project Dataset'!$G$2:$G$251,$I$2,'Final Project Dataset'!$C$2:$C$251,$I$3,'Final Project Dataset'!$B$2:$B$251,">="&MAX($A48,$I$4),'Final Project Dataset'!$B$2:$B$251,"<="&MIN(EOMONTH($A48,0),$I$5)) -> 0 | C48: =SUMIFS('Final Project Dataset'!$H$2:$H$251,'Final Project Dataset'!$G$2:$G$251,$I$2,'Final Project Dataset'!$C$2:$C$251,$I$3,'Final Project Dataset'!$B$2:$B$251,">="&MAX($A48,$I$4),'Final Project Dataset'!$B$2:$B$251,"<="&MIN(EOMONTH($A48,0),$I$5)) -> 0 | D48: =COUNTIFS('Final Project Dataset'!$G$2:$G$251,$I$2,'Final Project Dataset'!$C$2:$C$251,$I$3,'Final Project Dataset'!$B$2:$B$251,">="&MAX($A48,$I$4),'Final Project Dataset'!$B$2:$B$251,"<="&MIN(EOMONTH($A48,0),$I$5)) -> 0 | E48: =SUMIFS('Final Project Dataset'!$D$2:$D$251,'Final Project Dataset'!$G$2:$G$251,$I$2,'Final Project Dataset'!$C$2:$C$251,$I$3,'Final Project Dataset'!$B$2:$B$251,">="&MAX($A48,$I$4),'Final Project Dataset'!$B$2:$B$251,"<="&MIN(EOMONTH($A48,0),$I$5)) -> 0 | F48: =TEXT(A48,"mmm yy") -> Dec 25
A49: Grand Total | B49: =SUM(B37:B48) -> 89673 | C49: =SUM(C37:C48) -> 15915.68 | D49: =SUM(D37:D48) -> 3 | E49: =SUM(E37:E48) -> 11

Sheet FILTER_Demo
A1: Multi-Value Return (FILTER-style)
A2: Pick criteria; matching rows are returned below. Built with helper columns + INDEX/MATCH so it works in every Excel version.
A3: Region | B3: All | D3: Excel 365 equivalent (one formula, spills automatically):
A4: Product | B4: Tablet | D4: FILTER(Data[A2:K251], (Data[Region]=B3)*(Data[Product]=B4)*(Data[Sales]>=B5), "No match")
A5: Min sales (₹) | B5: 0 | D5: Showing the first 25 matches below.
A7: Matching rows | B7: =SUM('Final Project Dataset'!$S$2:$S$251) -> 22
A9: # | B9: Txn ID | C9: Date | D9: Product | E9: Qty | F9: Sales (₹) | G9: Region | H9: Profit (₹) | I9: Customer
A10: 1 | B10: =IFERROR(INDEX('Final Project Dataset'!$A$2:$A$251,MATCH($A10,'Final Project Dataset'!$T$2:$T$251,0)),"") -> T0003 | C10: =IFERROR(INDEX('Final Project Dataset'!$B$2:$B$251,MATCH($A10,'Final Project Dataset'!$T$2:$T$251,0)),"") -> 45661 | D10: =IFERROR(INDEX('Final Project Dataset'!$C$2:$C$251,MATCH($A10,'Final Project Dataset'!$T$2:$T$251,0)),"") -> Tablet | E10: =IFERROR(INDEX('Final Project Dataset'!$D$2:$D$251,MATCH($A10,'Final Project Dataset'!$T$2:$T$251,0)),"") -> 2 | F10: =IFERROR(INDEX('Final Project Dataset'!$F$2:$F$251,MATCH($A10,'Final Project Dataset'!$T$2:$T$251,0)),"") -> 34624 | G10: =IFERROR(INDEX('Final Project Dataset'!$G$2:$G$251,MATCH($A10,'Final Project Dataset'!$T$2:$T$251,0)),"") -> South | H10: =IFERROR(INDEX('Final Project Dataset'!$H$2:$H$251,MATCH($A10,'Final Project Dataset'!$T$2:$T$251,0)),"") -> 3946.53 | I10: =IFERROR(INDEX('Final Project Dataset'!$K$2:$K$251,MATCH($A10,'Final Project Dataset'!$T$2:$T$251,0)),"") -> Aditya Trivedi
A11: 2 | B11: =IFERROR(INDEX('Final Project Dataset'!$A$2:$A$251,MATCH($A11,'Final Project Dataset'!$T$2:$T$251,0)),"") -> T0020 | C11: =IFERROR(INDEX('Final Project Dataset'!$B$2:$B$251,MATCH($A11,'Final Project Dataset'!$T$2:$T$251,0)),"") -> 45689 | D11: =IFERROR(INDEX('Final Project Dataset'!$C$2:$C$251,MATCH($A11,'Final Project Dataset'!$T$2:$T$251,0)),"") -> Tablet | E11: =IFERROR(INDEX('Final Project Dataset'!$D$2:$D$251,MATCH($A11,'Final Project Dataset'!$T$2:$T$251,0)),"") -> 1 | F11: =IFERROR(INDEX('Final Project Dataset'!$F$2:$F$251,MATCH($A11,'Final Project Dataset'!$T$2:$T$251,0)),"") -> 16411 | G11: =IFERROR(INDEX('Final Project Dataset'!$G$2:$G$251,MATCH($A11,'Final Project Dataset'!$T$2:$T$251,0)),"") -> East | H11: =IFERROR(INDEX('Final Project Dataset'!$H$2:$H$251,MATCH($A11,'Final Project Dataset'!$T$2:$T$251,0)),"") -> 2520.3 | I11: =IFERROR(INDEX('Final Project Dataset'!$K$2:$K$251,MATCH($A11,'Final Project Dataset'!$T$2:$T$251,0)),"") -> Amit Singh
A12: 3 | B12: =IFERROR(INDEX('Final Project Dataset'!$A$2:$A$251,MATCH($A12,'Final Project Dataset'!$T$2:$T$251,0)),"") -> T0030 | C12: =IFERROR(INDEX('Final Project Dataset'!$B$2:$B$251,MATCH($A12,'Final Project Dataset'!$T$2:$T$251,0)),"") -> 45705 | D12: =IFERROR(INDEX('Final Project Dataset'!$C$2:$C$251,MATCH($A12,'Final Project Dataset'!$T$2:$T$251,0)),"") -> Tablet | E12: =IFERROR(INDEX('Final Project Dataset'!$D$2:$D$251,MATCH($A12,'Final Project Dataset'!$T$2:$T$251,0)),"") -> 1 | F12: =IFERROR(INDEX('Final Project Dataset'!$F$2:$F$251,MATCH($A12,'Final Project Dataset'!$T$2:$T$251,0)),"") -> 19646 | G12: =IFERROR(INDEX('Final Project Dataset'!$G$2:$G$251,MATCH($A12,'Final Project Dataset'!$T$2:$T$251,0)),"") -> West | H12: =IFERROR(INDEX('Final Project Dataset'!$H$2:$H$251,MATCH($A12,'Final Project Dataset'!$T$2:$T$251,0)),"") -> 2232.95 | I12: =IFERROR(INDEX('Final Project Dataset'!$K$2:$K$251,MATCH($A12,'Final Project Dataset'!$T$2:$T$251,0)),"") -> Vihaan Mehta
A13: 4 | B13: =IFERROR(INDEX('Final Project Dataset'!$A$2:$A$251,MATCH($A13,'Final Project Dataset'!$T$2:$T$251,0)),"") -> T0039 | C13: =IFERROR(INDEX('Final Project Dataset'!$B$2:$B$251,MATCH($A13,'Final Project Dataset'!$T$2:$T$251,0)),"") -> 45714 | D13: =IFERROR(INDEX('Final Project Dataset'!$C$2:$C$251,MATCH($A13,'Final Project Dataset'!$T$2:$T$251,0)),"") -> Tablet | E13: =IFERROR(INDEX('Final Project Dataset'!$D$2:$D$251,MATCH($A13,'Final Project Dataset'!$T$2:$T$251,0)),"") -> 1 | F13: =IFERROR(INDEX('Final Project Dataset'!$F$2:$F$251,MATCH($A13,'Final Project Dataset'!$T$2:$T$251,0)),"") -> 16260 | G13: =IFERROR(INDEX('Final Project Dataset'!$G$2:$G$251,MATCH($A13,'Final Project Dataset'!$T$2:$T$251,0)),"") -> West | H13: =IFERROR(INDEX('Final Project Dataset'!$H$2:$H$251,MATCH($A13,'Final Project Dataset'!$T$2:$T$251,0)),"") -> 1839.4 | I13: =IFERROR(INDEX('Final Project Dataset'!$K$2:$K$251,MATCH($A13,'Final Project Dataset'!$T$2:$T$251,0)),"") -> Nikhil Desai
A14: 5 | B14: =IFERROR(INDEX('Final Project Dataset'!$A$2:$A$251,MATCH($A14,'Final Project Dataset'!$T$2:$T$251,0)),"") -> T0040 | C14: =IFERROR(INDEX('Final Project Dataset'!$B$2:$B$251,MATCH($A14,'Final Project Dataset'!$T$2:$T$251,0)),"") -> 45716 | D14: =IFERROR(INDEX('Final Project Dataset'!$C$2:$C$251,MATCH($A14,'Final Project Dataset'!$T$2:$T$251,0)),"") -> Tablet | E14: =IFERROR(INDEX('Final Project Dataset'!$D$2:$D$251,MATCH($A14,'Final Project Dataset'!$T$2:$T$251,0)),"") -> 5 | F14: =IFERROR(INDEX('Final Project Dataset'!$F$2:$F$251,MATCH($A14,'Final Project Dataset'!$T$2:$T$251,0)),"") -> 96495 | G14: =IFERROR(INDEX('Final Project Dataset'!$G$2:$G$251,MATCH($A14,'Final Project Dataset'!$T$2:$T$251,0)),"") -> Central | H14: =IFERROR(INDEX('Final Project Dataset'!$H$2:$H$251,MATCH($A14,'Final Project Dataset'!$T$2:$T$251,0)),"") -> 7830.39 | I14: =IFERROR(INDEX('Final Project Dataset'!$K$2:$K$251,MATCH($A14,'Final Project Dataset'!$T$2:$T$251,0)),"") -> Meera Sharma
A15: 6 | B15: =IFERROR(INDEX('Final Project Dataset'!$A$2:$A$251,MATCH($A15,'Final Project Dataset'!$T$2:$T$251,0)),"") -> T0044 | C15: =IFERROR(INDEX('Final Project Dataset'!$B$2:$B$251,MATCH($A15,'Final Project Dataset'!$T$2:$T$251,0)),"") -> 45719 | D15: =IFERROR(INDEX('Final Project Dataset'!$C$2:$C$251,MATCH($A15,'Final Project Dataset'!$T$2:$T$251,0)),"") -> Tablet | E15: =IFERROR(INDEX('Final Project Dataset'!$D$2:$D$251,MATCH($A15,'Final Project Dataset'!$T$2:$T$251,0)),"") -> 1 | F15: =IFERROR(INDEX('Final Project Dataset'!$F$2:$F$251,MATCH($A15,'Final Project Dataset'!$T$2:$T$251,0)),"") -> 16634 | G15: =IFERROR(INDEX('Final Project Dataset'!$G$2:$G$251,MATCH($A15,'Final Project Dataset'!$T$2:$T$251,0)),"") -> Central | H15: =IFERROR(INDEX('Final Project Dataset'!$H$2:$H$251,MATCH($A15,'Final Project Dataset'!$T$2:$T$251,0)),"") -> 1651.06 | I15: =IFERROR(INDEX('Final Project Dataset'!$K$2:$K$251,MATCH($A15,'Final Project Dataset'!$T$2:$T$251,0)),"") -> Rohan Chauhan
A16: 7 | B16: =IFERROR(INDEX('Final Project Dataset'!$A$2:$A$251,MATCH($A16,'Final Project Dataset'!$T$2:$T$251,0)),"") -> T0051 | C16: =IFERROR(INDEX('Final Project Dataset'!$B$2:$B$251,MATCH($A16,'Final Project Dataset'!$T$2:$T$251,0)),"") -> 45725 | D16: =IFERROR(INDEX('Final Project Dataset'!$C$2:$C$251,MATCH($A16,'Final Project Dataset'!$T$2:$T$251,0)),"") -> Tablet | E16: =IFERROR(INDEX('Final Project Dataset'!$D$2:$D$251,MATCH($A16,'Final Project Dataset'!$T$2:$T$251,0)),"") -> 3 | F16: =IFERROR(INDEX('Final Project Dataset'!$F$2:$F$251,MATCH($A16,'Final Project Dataset'!$T$2:$T$251,0)),"") -> 48960 | G16: =IFERROR(INDEX('Final Project Dataset'!$G$2:$G$251,MATCH($A16,'Final Project Dataset'!$T$2:$T$251,0)),"") -> North | H16: =IFERROR(INDEX('Final Project Dataset'!$H$2:$H$251,MATCH($A16,'Final Project Dataset'!$T$2:$T$251,0)),"") -> 5703.16 | I16: =IFERROR(INDEX('Final Project Dataset'!$K$2:$K$251,MATCH($A16,'Final Project Dataset'!$T$2:$T$251,0)),"") -> Rohan Kapoor
A17: 8 | B17: =IFERROR(INDEX('Final Project Dataset'!$A$2:$A$251,MATCH($A17,'Final Project Dataset'!$T$2:$T$251,0)),"") -> T0054 | C17: =IFERROR(INDEX('Final Project Dataset'!$B$2:$B$251,MATCH($A17,'Final Project Dataset'!$T$2:$T$251,0)),"") -> 45727 | D17: =IFERROR(INDEX('Final Project Dataset'!$C$2:$C$251,MATCH($A17,'Final Project Dataset'!$T$2:$T$251,0)),"") -> Tablet | E17: =IFERROR(INDEX('Final Project Dataset'!$D$2:$D$251,MATCH($A17,'Final Project Dataset'!$T$2:$T$251,0)),"") -> 2 | F17: =IFERROR(INDEX('Final Project Dataset'!$F$2:$F$251,MATCH($A17,'Final Project Dataset'!$T$2:$T$251,0)),"") -> 39590 | G17: =IFERROR(INDEX('Final Project Dataset'!$G$2:$G$251,MATCH($A17,'Final Project Dataset'!$T$2:$T$251,0)),"") -> North | H17: =IFERROR(INDEX('Final Project Dataset'!$H$2:$H$251,MATCH($A17,'Final Project Dataset'!$T$2:$T$251,0)),"") -> 3959.71 | I17: =IFERROR(INDEX('Final Project Dataset'!$K$2:$K$251,MATCH($A17,'Final Project Dataset'!$T$2:$T$251,0)),"") -> Anjali Kapoor
A18: 9 | B18: =IFERROR(INDEX('Final Project Dataset'!$A$2:$A$251,MATCH($A18,'Final Project Dataset'!$T$2:$T$251,0)),"") -> T0092 | C18: =IFERROR(INDEX('Final Project Dataset'!$B$2:$B$251,MATCH($A18,'Final Project Dataset'!$T$2:$T$251,0)),"") -> 45793 | D18: =IFERROR(INDEX('Final Project Dataset'!$C$2:$C$251,MATCH($A18,'Final Project Dataset'!$T$2:$T$251,0)),"") -> Tablet | E18: =IFERROR(INDEX('Final Project Dataset'!$D$2:$D$251,MATCH($A18,'Final Project Dataset'!$T$2:$T$251,0)),"") -> 4 | F18: =IFERROR(INDEX('Final Project Dataset'!$F$2:$F$251,MATCH($A18,'Final Project Dataset'!$T$2:$T$251,0)),"") -> 66292 | G18: =IFERROR(INDEX('Final Project Dataset'!$G$2:$G$251,MATCH($A18,'Final Project Dataset'!$T$2:$T$251,0)),"") -> North | H18: =IFERROR(INDEX('Final Project Dataset'!$H$2:$H$251,MATCH($A18,'Final Project Dataset'!$T$2:$T$251,0)),"") -> 11124.64 | I18: =IFERROR(INDEX('Final Project Dataset'!$K$2:$K$251,MATCH($A18,'Final Project Dataset'!$T$2:$T$251,0)),"") -> Aditya Kapoor
A19: 10 | B19: =IFERROR(INDEX('Final Project Dataset'!$A$2:$A$251,MATCH($A19,'Final Project Dataset'!$T$2:$T$251,0)),"") -> T0099 | C19: =IFERROR(INDEX('Final Project Dataset'!$B$2:$B$251,MATCH($A19,'Final Project Dataset'!$T$2:$T$251,0)),"") -> 45805 | D19: =IFERROR(INDEX('Final Project Dataset'!$C$2:$C$251,MATCH($A19,'Final Project Dataset'!$T$2:$T$251,0)),"") -> Tablet | E19: =IFERROR(INDEX('Final Project Dataset'!$D$2:$D$251,MATCH($A19,'Final Project Dataset'!$T$2:$T$251,0)),"") -> 2 | F19: =IFERROR(INDEX('Final Project Dataset'!$F$2:$F$251,MATCH($A19,'Final Project Dataset'!$T$2:$T$251,0)),"") -> 38872 | G19: =IFERROR(INDEX('Final Project Dataset'!$G$2:$G$251,MATCH($A19,'Final Project Dataset'!$T$2:$T$251,0)),"") -> Central | H19: =IFERROR(INDEX('Final Project Dataset'!$H$2:$H$251,MATCH($A19,'Final Project Dataset'!$T$2:$T$251,0)),"") -> 4918.29 | I19: =IFERROR(INDEX('Final Project Dataset'!$K$2:$K$251,MATCH($A19,'Final Project Dataset'!$T$2:$T$251,0)),"") -> Ishita Iyer
A20: 11 | B20: =IFERROR(INDEX('Final Project Dataset'!$A$2:$A$251,MATCH($A20,'Final Project Dataset'!$T$2:$T$251,0)),"") -> T0118 | C20: =IFERROR(INDEX('Final Project Dataset'!$B$2:$B$251,MATCH($A20,'Final Project Dataset'!$T$2:$T$251,0)),"") -> 45835 | D20: =IFERROR(INDEX('Final Project Dataset'!$C$2:$C$251,MATCH($A20,'Final Project Dataset'!$T$2:$T$251,0)),"") -> Tablet | E20: =IFERROR(INDEX('Final Project Dataset'!$D$2:$D$251,MATCH($A20,'Final Project Dataset'!$T$2:$T$251,0)),"") -> 1 | F20: =IFERROR(INDEX('Final Project Dataset'!$F$2:$F$251,MATCH($A20,'Final Project Dataset'!$T$2:$T$251,0)),"") -> 17362 | G20: =IFERROR(INDEX('Final Project Dataset'!$G$2:$G$251,MATCH($A20,'Final Project Dataset'!$T$2:$T$251,0)),"") -> Central | H20: =IFERROR(INDEX('Final Project Dataset'!$H$2:$H$251,MATCH($A20,'Final Project Dataset'!$T$2:$T$251,0)),"") -> 2620.5 | I20: =IFERROR(INDEX('Final Project Dataset'!$K$2:$K$251,MATCH($A20,'Final Project Dataset'!$T$2:$T$251,0)),"") -> Riya Desai
A21: 12 | B21: =IFERROR(INDEX('Final Project Dataset'!$A$2:$A$251,MATCH($A21,'Final Project Dataset'!$T$2:$T$251,0)),"") -> T0135 | C21: =IFERROR(INDEX('Final Project Dataset'!$B$2:$B$251,MATCH($A21,'Final Project Dataset'!$T$2:$T$251,0)),"") -> 45852 | D21: =IFERROR(INDEX('Final Project Dataset'!$C$2:$C$251,MATCH($A21,'Final Project Dataset'!$T$2:$T$251,0)),"") -> Tablet | E21: =IFERROR(INDEX('Final Project Dataset'!$D$2:$D$251,MATCH($A21,'Final Project Dataset'!$T$2:$T$251,0)),"") -> 1 | F21: =IFERROR(INDEX('Final Project Dataset'!$F$2:$F$251,MATCH($A21,'Final Project Dataset'!$T$2:$T$251,0)),"") -> 16962 | G21: =IFERROR(INDEX('Final Project Dataset'!$G$2:$G$251,MATCH($A21,'Final Project Dataset'!$T$2:$T$251,0)),"") -> East | H21: =IFERROR(INDEX('Final Project Dataset'!$H$2:$H$251,MATCH($A21,'Final Project Dataset'!$T$2:$T$251,0)),"") -> 1911.36 | I21: =IFERROR(INDEX('Final Project Dataset'!$K$2:$K$251,MATCH($A21,'Final Project Dataset'!$T$2:$T$251,0)),"") -> Amit Iyer
... A34: 25 | B34: =IFERROR(INDEX('Final Project Dataset'!$A$2:$A$251,MATCH($A34,'Final Project Dataset'!$T$2:$T$251,0)),"") | C34: =IFERROR(INDEX('Final Project Dataset'!$B$2:$B$251,MATCH($A34,'Final Project Dataset'!$T$2:$T$251,0)),"") | D34: =IFERROR(INDEX('Final Project Dataset'!$C$2:$C$251,MATCH($A34,'Final Project Dataset'!$T$2:$T$251,0)),"") | E34: =IFERROR(INDEX('Final Project Dataset'!$D$2:$D$251,MATCH($A34,'Final Project Dataset'!$T$2:$T$251,0)),"") | F34: =IFERROR(INDEX('Final Project Dataset'!$F$2:$F$251,MATCH($A34,'Final Project Dataset'!$T$2:$T$251,0)),"") | G34: =IFERROR(INDEX('Final Project Dataset'!$G$2:$G$251,MATCH($A34,'Final Project Dataset'!$T$2:$T$251,0)),"") | H34: =IFERROR(INDEX('Final Project Dataset'!$H$2:$H$251,MATCH($A34,'Final Project Dataset'!$T$2:$T$251,0)),"") | I34: =IFERROR(INDEX('Final Project Dataset'!$K$2:$K$251,MATCH($A34,'Final Project Dataset'!$T$2:$T$251,0)),"")

Sheet High_Value_Customers
A1: High-Value Customers (GroupBy with SUMIF / COUNTIF)
A2: One row per customer ID; every figure is a formula over the dataset.
A3: High-value percentile | B3: 0.8 | D3: High-value customers | E3: =COUNTIF($J$8:$J$86,"High-Value") -> 16
A4: Sales threshold (₹) | B4: =PERCENTILE($D$8:$D$86,B3) -> 100178.4 | D4: Share of total sales | E4: =SUMIF($J$8:$J$86,"High-Value",$D$8:$D$86)/SUM($D$8:$D$86) -> 0.46198603
M6: Top 10 Customers
A7: Customer ID | B7: Customer Name | C7: Transactions | D7: Total Sales (₹) | E7: Total Profit (₹) | F7: Avg Sale (₹) | G7: Last Purchase | H7: Days Since (TODAY) | I7: Rank | J7: Tier | K7: Rank Key | M7: Rank | N7: Customer | O7: Sales (₹) | P7: Profit (₹) | Q7: Txns
A8: C001 | B8: =INDEX('Final Project Dataset'!$K$2:$K$251,MATCH(A8,'Final Project Dataset'!$I$2:$I$251,0)) -> Rahul Joshi | C8: =COUNTIF('Final Project Dataset'!$I$2:$I$251,A8) -> 1 | D8: =SUMIF('Final Project Dataset'!$I$2:$I$251,A8,'Final Project Dataset'!$F$2:$F$251) -> 17002 | E8: =SUMIF('Final Project Dataset'!$I$2:$I$251,A8,'Final Project Dataset'!$H$2:$H$251) -> 2606.4 | F8: =D8/C8 -> 17002 | G8: =_xlfn.MAXIFS('Final Project Dataset'!$B$2:$B$251,'Final Project Dataset'!$I$2:$I$251,A8) -> 45733 | H8: =TODAY()-G8 -> 592 | I8: =RANK(D8,$D$8:$D$86) -> 71 | J8: =IF(D8>=$B$4,"High-Value",IF(D8>=PERCENTILE($D$8:$D$86,0.5),"Mid-Value","Standard")) -> Standard | K8: =D8+ROW()/1000000 -> 17002 | M8: 1 | N8: =INDEX($B$8:$B$86,MATCH(LARGE($K$8:$K$86,$M8),$K$8:$K$86,0)) -> Aditya Kapoor | O8: =INDEX($D$8:$D$86,MATCH(LARGE($K$8:$K$86,$M8),$K$8:$K$86,0)) -> 321673 | P8: =INDEX($E$8:$E$86,MATCH(LARGE($K$8:$K$86,$M8),$K$8:$K$86,0)) -> 53148.24 | Q8: =INDEX($C$8:$C$86,MATCH(LARGE($K$8:$K$86,$M8),$K$8:$K$86,0)) -> 6
A9: C002 | B9: =INDEX('Final Project Dataset'!$K$2:$K$251,MATCH(A9,'Final Project Dataset'!$I$2:$I$251,0)) -> Karan Bhatt | C9: =COUNTIF('Final Project Dataset'!$I$2:$I$251,A9) -> 1 | D9: =SUMIF('Final Project Dataset'!$I$2:$I$251,A9,'Final Project Dataset'!$F$2:$F$251) -> 37464 | E9: =SUMIF('Final Project Dataset'!$I$2:$I$251,A9,'Final Project Dataset'!$H$2:$H$251) -> 6037.99 | F9: =D9/C9 -> 37464 | G9: =_xlfn.MAXIFS('Final Project Dataset'!$B$2:$B$251,'Final Project Dataset'!$I$2:$I$251,A9) -> 45992 | H9: =TODAY()-G9 -> 333 | I9: =RANK(D9,$D$8:$D$86) -> 53 | J9: =IF(D9>=$B$4,"High-Value",IF(D9>=PERCENTILE($D$8:$D$86,0.5),"Mid-Value","Standard")) -> Standard | K9: =D9+ROW()/1000000 -> 37464 | M9: 2 | N9: =INDEX($B$8:$B$86,MATCH(LARGE($K$8:$K$86,$M9),$K$8:$K$86,0)) -> Aditya Mehta | O9: =INDEX($D$8:$D$86,MATCH(LARGE($K$8:$K$86,$M9),$K$8:$K$86,0)) -> 249362 | P9: =INDEX($E$8:$E$86,MATCH(LARGE($K$8:$K$86,$M9),$K$8:$K$86,0)) -> 29285.42 | Q9: =INDEX($C$8:$C$86,MATCH(LARGE($K$8:$K$86,$M9),$K$8:$K$86,0)) -> 6
A10: C003 | B10: =INDEX('Final Project Dataset'!$K$2:$K$251,MATCH(A10,'Final Project Dataset'!$I$2:$I$251,0)) -> Kavya Reddy | C10: =COUNTIF('Final Project Dataset'!$I$2:$I$251,A10) -> 1 | D10: =SUMIF('Final Project Dataset'!$I$2:$I$251,A10,'Final Project Dataset'!$F$2:$F$251) -> 8668 | E10: =SUMIF('Final Project Dataset'!$I$2:$I$251,A10,'Final Project Dataset'!$H$2:$H$251) -> 1675.43 | F10: =D10/C10 -> 8668 | G10: =_xlfn.MAXIFS('Final Project Dataset'!$B$2:$B$251,'Final Project Dataset'!$I$2:$I$251,A10) -> 45857 | H10: =TODAY()-G10 -> 468 | I10: =RANK(D10,$D$8:$D$86) -> 74 | J10: =IF(D10>=$B$4,"High-Value",IF(D10>=PERCENTILE($D$8:$D$86,0.5),"Mid-Value","Standard")) -> Standard | K10: =D10+ROW()/1000000 -> 8668 | M10: 3 | N10: =INDEX($B$8:$B$86,MATCH(LARGE($K$8:$K$86,$M10),$K$8:$K$86,0)) -> Riya Reddy | O10: =INDEX($D$8:$D$86,MATCH(LARGE($K$8:$K$86,$M10),$K$8:$K$86,0)) -> 237530 | P10: =INDEX($E$8:$E$86,MATCH(LARGE($K$8:$K$86,$M10),$K$8:$K$86,0)) -> 34908.45 | Q10: =INDEX($C$8:$C$86,MATCH(LARGE($K$8:$K$86,$M10),$K$8:$K$86,0)) -> 8
A11: C004 | B11: =INDEX('Final Project Dataset'!$K$2:$K$251,MATCH(A11,'Final Project Dataset'!$I$2:$I$251,0)) -> Vihaan Nair | C11: =COUNTIF('Final Project Dataset'!$I$2:$I$251,A11) -> 4 | D11: =SUMIF('Final Project Dataset'!$I$2:$I$251,A11,'Final Project Dataset'!$F$2:$F$251) -> 58045 | E11: =SUMIF('Final Project Dataset'!$I$2:$I$251,A11,'Final Project Dataset'!$H$2:$H$251) -> 9221.05 | F11: =D11/C11 -> 14511.25 | G11: =_xlfn.MAXIFS('Final Project Dataset'!$B$2:$B$251,'Final Project Dataset'!$I$2:$I$251,A11) -> 45994 | H11: =TODAY()-G11 -> 331 | I11: =RANK(D11,$D$8:$D$86) -> 39 | J11: =IF(D11>=$B$4,"High-Value",IF(D11>=PERCENTILE($D$8:$D$86,0.5),"Mid-Value","Standard")) -> Mid-Value | K11: =D11+ROW()/1000000 -> 58045 | M11: 4 | N11: =INDEX($B$8:$B$86,MATCH(LARGE($K$8:$K$86,$M11),$K$8:$K$86,0)) -> Priya Iyer | O11: =INDEX($D$8:$D$86,MATCH(LARGE($K$8:$K$86,$M11),$K$8:$K$86,0)) -> 173827 | P11: =INDEX($E$8:$E$86,MATCH(LARGE($K$8:$K$86,$M11),$K$8:$K$86,0)) -> 28056.65 | Q11: =INDEX($C$8:$C$86,MATCH(LARGE($K$8:$K$86,$M11),$K$8:$K$86,0)) -> 4
A12: C005 | B12: =INDEX('Final Project Dataset'!$K$2:$K$251,MATCH(A12,'Final Project Dataset'!$I$2:$I$251,0)) -> Aditya Joshi | C12: =COUNTIF('Final Project Dataset'!$I$2:$I$251,A12) -> 2 | D12: =SUMIF('Final Project Dataset'!$I$2:$I$251,A12,'Final Project Dataset'!$F$2:$F$251) -> 52700 | E12: =SUMIF('Final Project Dataset'!$I$2:$I$251,A12,'Final Project Dataset'!$H$2:$H$251) -> 8671.15 | F12: =D12/C12 -> 26350 | G12: =_xlfn.MAXIFS('Final Project Dataset'!$B$2:$B$251,'Final Project Dataset'!$I$2:$I$251,A12) -> 45854 | H12: =TODAY()-G12 -> 471 | I12: =RANK(D12,$D$8:$D$86) -> 42 | J12: =IF(D12>=$B$4,"High-Value",IF(D12>=PERCENTILE($D$8:$D$86,0.5),"Mid-Value","Standard")) -> Standard | K12: =D12+ROW()/1000000 -> 52700 | M12: 5 | N12: =INDEX($B$8:$B$86,MATCH(LARGE($K$8:$K$86,$M12),$K$8:$K$86,0)) -> Vihaan Mehta | O12: =INDEX($D$8:$D$86,MATCH(LARGE($K$8:$K$86,$M12),$K$8:$K$86,0)) -> 153202 | P12: =INDEX($E$8:$E$86,MATCH(LARGE($K$8:$K$86,$M12),$K$8:$K$86,0)) -> 22319.83 | Q12: =INDEX($C$8:$C$86,MATCH(LARGE($K$8:$K$86,$M12),$K$8:$K$86,0)) -> 7
A13: C006 | B13: =INDEX('Final Project Dataset'!$K$2:$K$251,MATCH(A13,'Final Project Dataset'!$I$2:$I$251,0)) -> Riya Shah | C13: =COUNTIF('Final Project Dataset'!$I$2:$I$251,A13) -> 5 | D13: =SUMIF('Final Project Dataset'!$I$2:$I$251,A13,'Final Project Dataset'!$F$2:$F$251) -> 120001 | E13: =SUMIF('Final Project Dataset'!$I$2:$I$251,A13,'Final Project Dataset'!$H$2:$H$251) -> 15299.43 | F13: =D13/C13 -> 24000.2 | G13: =_xlfn.MAXIFS('Final Project Dataset'!$B$2:$B$251,'Final Project Dataset'!$I$2:$I$251,A13) -> 45999 | H13: =TODAY()-G13 -> 326 | I13: =RANK(D13,$D$8:$D$86) -> 9 | J13: =IF(D13>=$B$4,"High-Value",IF(D13>=PERCENTILE($D$8:$D$86,0.5),"Mid-Value","Standard")) -> High-Value | K13: =D13+ROW()/1000000 -> 120001 | M13: 6 | N13: =INDEX($B$8:$B$86,MATCH(LARGE($K$8:$K$86,$M13),$K$8:$K$86,0)) -> Anjali Patel | O13: =INDEX($D$8:$D$86,MATCH(LARGE($K$8:$K$86,$M13),$K$8:$K$86,0)) -> 139087 | P13: =INDEX($E$8:$E$86,MATCH(LARGE($K$8:$K$86,$M13),$K$8:$K$86,0)) -> 19635.71 | Q13: =INDEX($C$8:$C$86,MATCH(LARGE($K$8:$K$86,$M13),$K$8:$K$86,0)) -> 4
A14: C007 | B14: =INDEX('Final Project Dataset'!$K$2:$K$251,MATCH(A14,'Final Project Dataset'!$I$2:$I$251,0)) -> Rohan Sharma | C14: =COUNTIF('Final Project Dataset'!$I$2:$I$251,A14) -> 4 | D14: =SUMIF('Final Project Dataset'!$I$2:$I$251,A14,'Final Project Dataset'!$F$2:$F$251) -> 29460 | E14: =SUMIF('Final Project Dataset'!$I$2:$I$251,A14,'Final Project Dataset'!$H$2:$H$251) -> 5498.5 | F14: =D14/C14 -> 7365 | G14: =_xlfn.MAXIFS('Final Project Dataset'!$B$2:$B$251,'Final Project Dataset'!$I$2:$I$251,A14) -> 45998 | H14: =TODAY()-G14 -> 327 | I14: =RANK(D14,$D$8:$D$86) -> 57 | J14: =IF(D14>=$B$4,"High-Value",IF(D14>=PERCENTILE($D$8:$D$86,0.5),"Mid-Value","Standard")) -> Standard | K14: =D14+ROW()/1000000 -> 29460 | M14: 7 | N14: =INDEX($B$8:$B$86,MATCH(LARGE($K$8:$K$86,$M14),$K$8:$K$86,0)) -> Sanjay Reddy | O14: =INDEX($D$8:$D$86,MATCH(LARGE($K$8:$K$86,$M14),$K$8:$K$86,0)) -> 134149 | P14: =INDEX($E$8:$E$86,MATCH(LARGE($K$8:$K$86,$M14),$K$8:$K$86,0)) -> 23456.42 | Q14: =INDEX($C$8:$C$86,MATCH(LARGE($K$8:$K$86,$M14),$K$8:$K$86,0)) -> 5
A15: C008 | B15: =INDEX('Final Project Dataset'!$K$2:$K$251,MATCH(A15,'Final Project Dataset'!$I$2:$I$251,0)) -> Amit Singh | C15: =COUNTIF('Final Project Dataset'!$I$2:$I$251,A15) -> 5 | D15: =SUMIF('Final Project Dataset'!$I$2:$I$251,A15,'Final Project Dataset'!$F$2:$F$251) -> 116671 | E15: =SUMIF('Final Project Dataset'!$I$2:$I$251,A15,'Final Project Dataset'!$H$2:$H$251) -> 20018.63 | F15: =D15/C15 -> 23334.2 | G15: =_xlfn.MAXIFS('Final Project Dataset'!$B$2:$B$251,'Final Project Dataset'!$I$2:$I$251,A15) -> 45988 | H15: =TODAY()-G15 -> 337 | I15: =RANK(D15,$D$8:$D$86) -> 11 | J15: =IF(D15>=$B$4,"High-Value",IF(D15>=PERCENTILE($D$8:$D$86,0.5),"Mid-Value","Standard")) -> High-Value | K15: =D15+ROW()/1000000 -> 116671 | M15: 8 | N15: =INDEX($B$8:$B$86,MATCH(LARGE($K$8:$K$86,$M15),$K$8:$K$86,0)) -> Sneha Trivedi | O15: =INDEX($D$8:$D$86,MATCH(LARGE($K$8:$K$86,$M15),$K$8:$K$86,0)) -> 125952 | P15: =INDEX($E$8:$E$86,MATCH(LARGE($K$8:$K$86,$M15),$K$8:$K$86,0)) -> 13944.02 | Q15: =INDEX($C$8:$C$86,MATCH(LARGE($K$8:$K$86,$M15),$K$8:$K$86,0)) -> 2
A16: C009 | B16: =INDEX('Final Project Dataset'!$K$2:$K$251,MATCH(A16,'Final Project Dataset'!$I$2:$I$251,0)) -> Sanjay Reddy | C16: =COUNTIF('Final Project Dataset'!$I$2:$I$251,A16) -> 5 | D16: =SUMIF('Final Project Dataset'!$I$2:$I$251,A16,'Final Project Dataset'!$F$2:$F$251) -> 134149 | E16: =SUMIF('Final Project Dataset'!$I$2:$I$251,A16,'Final Project Dataset'!$H$2:$H$251) -> 23456.42 | F16: =D16/C16 -> 26829.8 | G16: =_xlfn.MAXIFS('Final Project Dataset'!$B$2:$B$251,'Final Project Dataset'!$I$2:$I$251,A16) -> 46009 | H16: =TODAY()-G16 -> 316 | I16: =RANK(D16,$D$8:$D$86) -> 7 | J16: =IF(D16>=$B$4,"High-Value",IF(D16>=PERCENTILE($D$8:$D$86,0.5),"Mid-Value","Standard")) -> High-Value | K16: =D16+ROW()/1000000 -> 134149 | M16: 9 | N16: =INDEX($B$8:$B$86,MATCH(LARGE($K$8:$K$86,$M16),$K$8:$K$86,0)) -> Riya Shah | O16: =INDEX($D$8:$D$86,MATCH(LARGE($K$8:$K$86,$M16),$K$8:$K$86,0)) -> 120001 | P16: =INDEX($E$8:$E$86,MATCH(LARGE($K$8:$K$86,$M16),$K$8:$K$86,0)) -> 15299.43 | Q16: =INDEX($C$8:$C$86,MATCH(LARGE($K$8:$K$86,$M16),$K$8:$K$86,0)) -> 5
A17: C010 | B17: =INDEX('Final Project Dataset'!$K$2:$K$251,MATCH(A17,'Final Project Dataset'!$I$2:$I$251,0)) -> Vihaan Bhatt | C17: =COUNTIF('Final Project Dataset'!$I$2:$I$251,A17) -> 4 | D17: =SUMIF('Final Project Dataset'!$I$2:$I$251,A17,'Final Project Dataset'!$F$2:$F$251) -> 83654 | E17: =SUMIF('Final Project Dataset'!$I$2:$I$251,A17,'Final Project Dataset'!$H$2:$H$251) -> 10906.08 | F17: =D17/C17 -> 20913.5 | G17: =_xlfn.MAXIFS('Final Project Dataset'!$B$2:$B$251,'Final Project Dataset'!$I$2:$I$251,A17) -> 45867 | H17: =TODAY()-G17 -> 458 | I17: =RANK(D17,$D$8:$D$86) -> 19 | J17: =IF(D17>=$B$4,"High-Value",IF(D17>=PERCENTILE($D$8:$D$86,0.5),"Mid-Value","Standard")) -> Mid-Value | K17: =D17+ROW()/1000000 -> 83654 | M17: 10 | N17: =INDEX($B$8:$B$86,MATCH(LARGE($K$8:$K$86,$M17),$K$8:$K$86,0)) -> Aditya Iyer | O17: =INDEX($D$8:$D$86,MATCH(LARGE($K$8:$K$86,$M17),$K$8:$K$86,0)) -> 118548 | P17: =INDEX($E$8:$E$86,MATCH(LARGE($K$8:$K$86,$M17),$K$8:$K$86,0)) -> 18036.54 | Q17: =INDEX($C$8:$C$86,MATCH(LARGE($K$8:$K$86,$M17),$K$8:$K$86,0)) -> 5
A18: C011 | B18: =INDEX('Final Project Dataset'!$K$2:$K$251,MATCH(A18,'Final Project Dataset'!$I$2:$I$251,0)) -> Nikhil Mehta | C18: =COUNTIF('Final Project Dataset'!$I$2:$I$251,A18) -> 3 | D18: =SUMIF('Final Project Dataset'!$I$2:$I$251,A18,'Final Project Dataset'!$F$2:$F$251) -> 27234 | E18: =SUMIF('Final Project Dataset'!$I$2:$I$251,A18,'Final Project Dataset'!$H$2:$H$251) -> 3748.22 | F18: =D18/C18 -> 9078 | G18: =_xlfn.MAXIFS('Final Project Dataset'!$B$2:$B$251,'Final Project Dataset'!$I$2:$I$251,A18) -> 45821 | H18: =TODAY()-G18 -> 504 | I18: =RANK(D18,$D$8:$D$86) -> 60 | J18: =IF(D18>=$B$4,"High-Value",IF(D18>=PERCENTILE($D$8:$D$86,0.5),"Mid-Value","Standard")) -> Standard | K18: =D18+ROW()/1000000 -> 27234
A19: C012 | B19: =INDEX('Final Project Dataset'!$K$2:$K$251,MATCH(A19,'Final Project Dataset'!$I$2:$I$251,0)) -> Priya Bhatt | C19: =COUNTIF('Final Project Dataset'!$I$2:$I$251,A19) -> 2 | D19: =SUMIF('Final Project Dataset'!$I$2:$I$251,A19,'Final Project Dataset'!$F$2:$F$251) -> 42467 | E19: =SUMIF('Final Project Dataset'!$I$2:$I$251,A19,'Final Project Dataset'!$H$2:$H$251) -> 5140.33 | F19: =D19/C19 -> 21233.5 | G19: =_xlfn.MAXIFS('Final Project Dataset'!$B$2:$B$251,'Final Project Dataset'!$I$2:$I$251,A19) -> 45723 | H19: =TODAY()-G19 -> 602 | I19: =RANK(D19,$D$8:$D$86) -> 49 | J19: =IF(D19>=$B$4,"High-Value",IF(D19>=PERCENTILE($D$8:$D$86,0.5),"Mid-Value","Standard")) -> Standard | K19: =D19+ROW()/1000000 -> 42467
A20: C013 | B20: =INDEX('Final Project Dataset'!$K$2:$K$251,MATCH(A20,'Final Project Dataset'!$I$2:$I$251,0)) -> Vihaan Mehta | C20: =COUNTIF('Final Project Dataset'!$I$2:$I$251,A20) -> 7 | D20: =SUMIF('Final Project Dataset'!$I$2:$I$251,A20,'Final Project Dataset'!$F$2:$F$251) -> 153202 | E20: =SUMIF('Final Project Dataset'!$I$2:$I$251,A20,'Final Project Dataset'!$H$2:$H$251) -> 22319.83 | F20: =D20/C20 -> 21886 | G20: =_xlfn.MAXIFS('Final Project Dataset'!$B$2:$B$251,'Final Project Dataset'!$I$2:$I$251,A20) -> 45910 | H20: =TODAY()-G20 -> 415 | I20: =RANK(D20,$D$8:$D$86) -> 5 | J20: =IF(D20>=$B$4,"High-Value",IF(D20>=PERCENTILE($D$8:$D$86,0.5),"Mid-Value","Standard")) -> High-Value | K20: =D20+ROW()/1000000 -> 153202
A21: C014 | B21: =INDEX('Final Project Dataset'!$K$2:$K$251,MATCH(A21,'Final Project Dataset'!$I$2:$I$251,0)) -> Aditya Kapoor | C21: =COUNTIF('Final Project Dataset'!$I$2:$I$251,A21) -> 6 | D21: =SUMIF('Final Project Dataset'!$I$2:$I$251,A21,'Final Project Dataset'!$F$2:$F$251) -> 321673 | E21: =SUMIF('Final Project Dataset'!$I$2:$I$251,A21,'Final Project Dataset'!$H$2:$H$251) -> 53148.24 | F21: =D21/C21 -> 53612.167 | G21: =_xlfn.MAXIFS('Final Project Dataset'!$B$2:$B$251,'Final Project Dataset'!$I$2:$I$251,A21) -> 46011 | H21: =TODAY()-G21 -> 314 | I21: =RANK(D21,$D$8:$D$86) -> 1 | J21: =IF(D21>=$B$4,"High-Value",IF(D21>=PERCENTILE($D$8:$D$86,0.5),"Mid-Value","Standard")) -> High-Value | K21: =D21+ROW()/1000000 -> 321673
A22: C015 | B22: =INDEX('Final Project Dataset'!$K$2:$K$251,MATCH(A22,'Final Project Dataset'!$I$2:$I$251,0)) -> Ishita Trivedi | C22: =COUNTIF('Final Project Dataset'!$I$2:$I$251,A22) -> 2 | D22: =SUMIF('Final Project Dataset'!$I$2:$I$251,A22,'Final Project Dataset'!$F$2:$F$251) -> 5706 | E22: =SUMIF('Final Project Dataset'!$I$2:$I$251,A22,'Final Project Dataset'!$H$2:$H$251) -> 1480.99 | F22: =D22/C22 -> 2853 | G22: =_xlfn.MAXIFS('Final Project Dataset'!$B$2:$B$251,'Final Project Dataset'!$I$2:$I$251,A22) -> 45809 | H22: =TODAY()-G22 -> 516 | I22: =RANK(D22,$D$8:$D$86) -> 76 | J22: =IF(D22>=$B$4,"High-Value",IF(D22>=PERCENTILE($D$8:$D$86,0.5),"Mid-Value","Standard")) -> Standard | K22: =D22+ROW()/1000000 -> 5706
A23: C016 | B23: =INDEX('Final Project Dataset'!$K$2:$K$251,MATCH(A23,'Final Project Dataset'!$I$2:$I$251,0)) -> Ishita Verma | C23: =COUNTIF('Final Project Dataset'!$I$2:$I$251,A23) -> 2 | D23: =SUMIF('Final Project Dataset'!$I$2:$I$251,A23,'Final Project Dataset'!$F$2:$F$251) -> 73493 | E23: =SUMIF('Final Project Dataset'!$I$2:$I$251,A23,'Final Project Dataset'!$H$2:$H$251) -> 11683.62 | F23: =D23/C23 -> 36746.5 | G23: =_xlfn.MAXIFS('Final Project Dataset'!$B$2:$B$251,'Final Project Dataset'!$I$2:$I$251,A23) -> 46015 | H23: =TODAY()-G23 -> 310 | I23: =RANK(D23,$D$8:$D$86) -> 28 | J23: =IF(D23>=$B$4,"High-Value",IF(D23>=PERCENTILE($D$8:$D$86,0.5),"Mid-Value","Standard")) -> Mid-Value | K23: =D23+ROW()/1000000 -> 73493
A24: C017 | B24: =INDEX('Final Project Dataset'!$K$2:$K$251,MATCH(A24,'Final Project Dataset'!$I$2:$I$251,0)) -> Aditya Mehta | C24: =COUNTIF('Final Project Dataset'!$I$2:$I$251,A24) -> 6 | D24: =SUMIF('Final Project Dataset'!$I$2:$I$251,A24,'Final Project Dataset'!$F$2:$F$251) -> 249362 | E24: =SUMIF('Final Project Dataset'!$I$2:$I$251,A24,'Final Project Dataset'!$H$2:$H$251) -> 29285.42 | F24: =D24/C24 -> 41560.333 | G24: =_xlfn.MAXIFS('Final Project Dataset'!$B$2:$B$251,'Final Project Dataset'!$I$2:$I$251,A24) -> 46020 | H24: =TODAY()-G24 -> 305 | I24: =RANK(D24,$D$8:$D$86) -> 2 | J24: =IF(D24>=$B$4,"High-Value",IF(D24>=PERCENTILE($D$8:$D$86,0.5),"Mid-Value","Standard")) -> High-Value | K24: =D24+ROW()/1000000 -> 249362
A25: C018 | B25: =INDEX('Final Project Dataset'!$K$2:$K$251,MATCH(A25,'Final Project Dataset'!$I$2:$I$251,0)) -> Anjali Singh | C25: =COUNTIF('Final Project Dataset'!$I$2:$I$251,A25) -> 2 | D25: =SUMIF('Final Project Dataset'!$I$2:$I$251,A25,'Final Project Dataset'!$F$2:$F$251) -> 12605 | E25: =SUMIF('Final Project Dataset'!$I$2:$I$251,A25,'Final Project Dataset'!$H$2:$H$251) -> 3049.43 | F25: =D25/C25 -> 6302.5 | G25: =_xlfn.MAXIFS('Final Project Dataset'!$B$2:$B$251,'Final Project Dataset'!$I$2:$I$251,A25) -> 45932 | H25: =TODAY()-G25 -> 393 | I25: =RANK(D25,$D$8:$D$86) -> 72 | J25: =IF(D25>=$B$4,"High-Value",IF(D25>=PERCENTILE($D$8:$D$86,0.5),"Mid-Value","Standard")) -> Standard | K25: =D25+ROW()/1000000 -> 12605
A26: C019 | B26: =INDEX('Final Project Dataset'!$K$2:$K$251,MATCH(A26,'Final Project Dataset'!$I$2:$I$251,0)) -> Aditya Trivedi | C26: =COUNTIF('Final Project Dataset'!$I$2:$I$251,A26) -> 3 | D26: =SUMIF('Final Project Dataset'!$I$2:$I$251,A26,'Final Project Dataset'!$F$2:$F$251) -> 84089 | E26: =SUMIF('Final Project Dataset'!$I$2:$I$251,A26,'Final Project Dataset'!$H$2:$H$251) -> 10207.96 | F26: =D26/C26 -> 28029.667 | G26: =_xlfn.MAXIFS('Final Project Dataset'!$B$2:$B$251,'Final Project Dataset'!$I$2:$I$251,A26) -> 45987 | H26: =TODAY()-G26 -> 338 | I26: =RANK(D26,$D$8:$D$86) -> 18 | J26: =IF(D26>=$B$4,"High-Value",IF(D26>=PERCENTILE($D$8:$D$86,0.5),"Mid-Value","Standard")) -> Mid-Value | K26: =D26+ROW()/1000000 -> 84089
A27: C020 | B27: =INDEX('Final Project Dataset'!$K$2:$K$251,MATCH(A27,'Final Project Dataset'!$I$2:$I$251,0)) -> Riya Reddy | C27: =COUNTIF('Final Project Dataset'!$I$2:$I$251,A27) -> 8 | D27: =SUMIF('Final Project Dataset'!$I$2:$I$251,A27,'Final Project Dataset'!$F$2:$F$251) -> 237530 | E27: =SUMIF('Final Project Dataset'!$I$2:$I$251,A27,'Final Project Dataset'!$H$2:$H$251) -> 34908.45 | F27: =D27/C27 -> 29691.25 | G27: =_xlfn.MAXIFS('Final Project Dataset'!$B$2:$B$251,'Final Project Dataset'!$I$2:$I$251,A27) -> 45969 | H27: =TODAY()-G27 -> 356 | I27: =RANK(D27,$D$8:$D$86) -> 3 | J27: =IF(D27>=$B$4,"High-Value",IF(D27>=PERCENTILE($D$8:$D$86,0.5),"Mid-Value","Standard")) -> High-Value | K27: =D27+ROW()/1000000 -> 237530
A28: C021 | B28: =INDEX('Final Project Dataset'!$K$2:$K$251,MATCH(A28,'Final Project Dataset'!$I$2:$I$251,0)) -> Ishita Iyer | C28: =COUNTIF('Final Project Dataset'!$I$2:$I$251,A28) -> 4 | D28: =SUMIF('Final Project Dataset'!$I$2:$I$251,A28,'Final Project Dataset'!$F$2:$F$251) -> 78914 | E28: =SUMIF('Final Project Dataset'!$I$2:$I$251,A28,'Final Project Dataset'!$H$2:$H$251) -> 12227.56 | F28: =D28/C28 -> 19728.5 | G28: =_xlfn.MAXIFS('Final Project Dataset'!$B$2:$B$251,'Final Project Dataset'!$I$2:$I$251,A28) -> 45971 | H28: =TODAY()-G28 -> 354 | I28: =RANK(D28,$D$8:$D$86) -> 24 | J28: =IF(D28>=$B$4,"High-Value",IF(D28>=PERCENTILE($D$8:$D$86,0.5),"Mid-Value","Standard")) -> Mid-Value | K28: =D28+ROW()/1000000 -> 78914
A29: C022 | B29: =INDEX('Final Project Dataset'!$K$2:$K$251,MATCH(A29,'Final Project Dataset'!$I$2:$I$251,0)) -> Vihaan Trivedi | C29: =COUNTIF('Final Project Dataset'!$I$2:$I$251,A29) -> 1 | D29: =SUMIF('Final Project Dataset'!$I$2:$I$251,A29,'Final Project Dataset'!$F$2:$F$251) -> 4735 | E29: =SUMIF('Final Project Dataset'!$I$2:$I$251,A29,'Final Project Dataset'!$H$2:$H$251) -> 1517.04 | F29: =D29/C29 -> 4735 | G29: =_xlfn.MAXIFS('Final Project Dataset'!$B$2:$B$251,'Final Project Dataset'!$I$2:$I$251,A29) -> 45709 | H29: =TODAY()-G29 -> 616 | I29: =RANK(D29,$D$8:$D$86) -> 78 | J29: =IF(D29>=$B$4,"High-Value",IF(D29>=PERCENTILE($D$8:$D$86,0.5),"Mid-Value","Standard")) -> Standard | K29: =D29+ROW()/1000000 -> 4735
... A86: C080 | B86: =INDEX('Final Project Dataset'!$K$2:$K$251,MATCH(A86,'Final Project Dataset'!$I$2:$I$251,0)) -> Sneha Trivedi | C86: =COUNTIF('Final Project Dataset'!$I$2:$I$251,A86) -> 2 | D86: =SUMIF('Final Project Dataset'!$I$2:$I$251,A86,'Final Project Dataset'!$F$2:$F$251) -> 125952 | E86: =SUMIF('Final Project Dataset'!$I$2:$I$251,A86,'Final Project Dataset'!$H$2:$H$251) -> 13944.02 | F86: =D86/C86 -> 62976 | G86: =_xlfn.MAXIFS('Final Project Dataset'!$B$2:$B$251,'Final Project Dataset'!$I$2:$I$251,A86) -> 45736 | H86: =TODAY()-G86 -> 589 | I86: =RANK(D86,$D$8:$D$86) -> 8 | J86: =IF(D86>=$B$4,"High-Value",IF(D86>=PERCENTILE($D$8:$D$86,0.5),"Mid-Value","Standard")) -> High-Value | K86: =D86+ROW()/1000000 -> 125952

Sheet Frequency_Match
A1: Frequency Analysis & List Comparison
H2: Compare two lists: Mailing List (A) vs Customer Names (B)
A3: Product | B3: Times Purchased | C3: Units Sold | D3: Rank | E3: Share of Txns | F3: Top flag | H3: Mailing List (A) | I3: In Customers? (B) | J3: Matched Name | K3: Extract # | L3: Extracted Matches
A4: Laptop | B4: =COUNTIF('Final Project Dataset'!$C$2:$C$251,A4) -> 19 | C4: =SUMIF('Final Project Dataset'!$C$2:$C$251,A4,'Final Project Dataset'!$D$2:$D$251) -> 31 | D4: =RANK(B4,$B$4:$B$13) -> 10 | E4: =B4/SUM($B$4:$B$13) -> 0.076 | F4: =IF(B4=MAX($B$4:$B$13),A4&", ","") | H4: Priya Bhatt | I4: =IF(COUNTIF(High_Value_Customers!$B$8:$B$86,H4)>0,"Match","No match") -> Match | J4: =IF(I4="Match",H4,"") -> Priya Bhatt | K4: =IF(J4<>"",COUNTIF(J$4:J4,"?*"),"") -> 1 | L4: =IFERROR(INDEX($J$4:$J$33,MATCH(ROWS(L$4:L4),$K$4:$K$33,0)),"") -> Priya Bhatt
A5: Smartphone | B5: =COUNTIF('Final Project Dataset'!$C$2:$C$251,A5) -> 29 | C5: =SUMIF('Final Project Dataset'!$C$2:$C$251,A5,'Final Project Dataset'!$D$2:$D$251) -> 45 | D5: =RANK(B5,$B$4:$B$13) -> 3 | E5: =B5/SUM($B$4:$B$13) -> 0.116 | F5: =IF(B5=MAX($B$4:$B$13),A5&", ","") | H5: Kavya Reddy | I5: =IF(COUNTIF(High_Value_Customers!$B$8:$B$86,H5)>0,"Match","No match") -> Match | J5: =IF(I5="Match",H5,"") -> Kavya Reddy | K5: =IF(J5<>"",COUNTIF(J$4:J5,"?*"),"") -> 2 | L5: =IFERROR(INDEX($J$4:$J$33,MATCH(ROWS(L$4:L5),$K$4:$K$33,0)),"") -> Kavya Reddy
A6: Monitor | B6: =COUNTIF('Final Project Dataset'!$C$2:$C$251,A6) -> 30 | C6: =SUMIF('Final Project Dataset'!$C$2:$C$251,A6,'Final Project Dataset'!$D$2:$D$251) -> 69 | D6: =RANK(B6,$B$4:$B$13) -> 1 | E6: =B6/SUM($B$4:$B$13) -> 0.12 | F6: =IF(B6=MAX($B$4:$B$13),A6&", ","") -> Monitor, | H6: Rohan Kapoor | I6: =IF(COUNTIF(High_Value_Customers!$B$8:$B$86,H6)>0,"Match","No match") -> Match | J6: =IF(I6="Match",H6,"") -> Rohan Kapoor | K6: =IF(J6<>"",COUNTIF(J$4:J6,"?*"),"") -> 3 | L6: =IFERROR(INDEX($J$4:$J$33,MATCH(ROWS(L$4:L6),$K$4:$K$33,0)),"") -> Rohan Kapoor
A7: Tablet | B7: =COUNTIF('Final Project Dataset'!$C$2:$C$251,A7) -> 22 | C7: =SUMIF('Final Project Dataset'!$C$2:$C$251,A7,'Final Project Dataset'!$D$2:$D$251) -> 45 | D7: =RANK(B7,$B$4:$B$13) -> 7 | E7: =B7/SUM($B$4:$B$13) -> 0.088 | F7: =IF(B7=MAX($B$4:$B$13),A7&", ","") | H7: Rahul Sharma | I7: =IF(COUNTIF(High_Value_Customers!$B$8:$B$86,H7)>0,"Match","No match") -> Match | J7: =IF(I7="Match",H7,"") -> Rahul Sharma | K7: =IF(J7<>"",COUNTIF(J$4:J7,"?*"),"") -> 4 | L7: =IFERROR(INDEX($J$4:$J$33,MATCH(ROWS(L$4:L7),$K$4:$K$33,0)),"") -> Rahul Sharma
A8: Smartwatch | B8: =COUNTIF('Final Project Dataset'!$C$2:$C$251,A8) -> 24 | C8: =SUMIF('Final Project Dataset'!$C$2:$C$251,A8,'Final Project Dataset'!$D$2:$D$251) -> 56 | D8: =RANK(B8,$B$4:$B$13) -> 6 | E8: =B8/SUM($B$4:$B$13) -> 0.096 | F8: =IF(B8=MAX($B$4:$B$13),A8&", ","") | H8: Aarav Reddy | I8: =IF(COUNTIF(High_Value_Customers!$B$8:$B$86,H8)>0,"Match","No match") -> Match | J8: =IF(I8="Match",H8,"") -> Aarav Reddy | K8: =IF(J8<>"",COUNTIF(J$4:J8,"?*"),"") -> 5 | L8: =IFERROR(INDEX($J$4:$J$33,MATCH(ROWS(L$4:L8),$K$4:$K$33,0)),"") -> Aarav Reddy
A9: Printer | B9: =COUNTIF('Final Project Dataset'!$C$2:$C$251,A9) -> 22 | C9: =SUMIF('Final Project Dataset'!$C$2:$C$251,A9,'Final Project Dataset'!$D$2:$D$251) -> 34 | D9: =RANK(B9,$B$4:$B$13) -> 7 | E9: =B9/SUM($B$4:$B$13) -> 0.088 | F9: =IF(B9=MAX($B$4:$B$13),A9&", ","") | H9: Neha Iyer | I9: =IF(COUNTIF(High_Value_Customers!$B$8:$B$86,H9)>0,"Match","No match") -> No match | J9: =IF(I9="Match",H9,"") | K9: =IF(J9<>"",COUNTIF(J$4:J9,"?*"),"") | L9: =IFERROR(INDEX($J$4:$J$33,MATCH(ROWS(L$4:L9),$K$4:$K$33,0)),"") -> Nikhil Bhatt
A10: Headphones | B10: =COUNTIF('Final Project Dataset'!$C$2:$C$251,A10) -> 30 | C10: =SUMIF('Final Project Dataset'!$C$2:$C$251,A10,'Final Project Dataset'!$D$2:$D$251) -> 54 | D10: =RANK(B10,$B$4:$B$13) -> 1 | E10: =B10/SUM($B$4:$B$13) -> 0.12 | F10: =IF(B10=MAX($B$4:$B$13),A10&", ","") -> Headphones, | H10: Nikhil Iyer | I10: =IF(COUNTIF(High_Value_Customers!$B$8:$B$86,H10)>0,"Match","No match") -> No match | J10: =IF(I10="Match",H10,"") | K10: =IF(J10<>"",COUNTIF(J$4:J10,"?*"),"") | L10: =IFERROR(INDEX($J$4:$J$33,MATCH(ROWS(L$4:L10),$K$4:$K$33,0)),"") -> Nikhil Mehta
A11: Webcam | B11: =COUNTIF('Final Project Dataset'!$C$2:$C$251,A11) -> 25 | C11: =SUMIF('Final Project Dataset'!$C$2:$C$251,A11,'Final Project Dataset'!$D$2:$D$251) -> 56 | D11: =RANK(B11,$B$4:$B$13) -> 5 | E11: =B11/SUM($B$4:$B$13) -> 0.1 | F11: =IF(B11=MAX($B$4:$B$13),A11&", ","") | H11: Amit Patel | I11: =IF(COUNTIF(High_Value_Customers!$B$8:$B$86,H11)>0,"Match","No match") -> No match | J11: =IF(I11="Match",H11,"") | K11: =IF(J11<>"",COUNTIF(J$4:J11,"?*"),"") | L11: =IFERROR(INDEX($J$4:$J$33,MATCH(ROWS(L$4:L11),$K$4:$K$33,0)),"") -> Karan Desai
A12: Keyboard | B12: =COUNTIF('Final Project Dataset'!$C$2:$C$251,A12) -> 27 | C12: =SUMIF('Final Project Dataset'!$C$2:$C$251,A12,'Final Project Dataset'!$D$2:$D$251) -> 50 | D12: =RANK(B12,$B$4:$B$13) -> 4 | E12: =B12/SUM($B$4:$B$13) -> 0.108 | F12: =IF(B12=MAX($B$4:$B$13),A12&", ","") | H12: Nikhil Bhatt | I12: =IF(COUNTIF(High_Value_Customers!$B$8:$B$86,H12)>0,"Match","No match") -> Match | J12: =IF(I12="Match",H12,"") -> Nikhil Bhatt | K12: =IF(J12<>"",COUNTIF(J$4:J12,"?*"),"") -> 6 | L12: =IFERROR(INDEX($J$4:$J$33,MATCH(ROWS(L$4:L12),$K$4:$K$33,0)),"") -> Aditya Verma
A13: Mouse | B13: =COUNTIF('Final Project Dataset'!$C$2:$C$251,A13) -> 22 | C13: =SUMIF('Final Project Dataset'!$C$2:$C$251,A13,'Final Project Dataset'!$D$2:$D$251) -> 44 | D13: =RANK(B13,$B$4:$B$13) -> 7 | E13: =B13/SUM($B$4:$B$13) -> 0.088 | F13: =IF(B13=MAX($B$4:$B$13),A13&", ","") | H13: Nikhil Mehta | I13: =IF(COUNTIF(High_Value_Customers!$B$8:$B$86,H13)>0,"Match","No match") -> Match | J13: =IF(I13="Match",H13,"") -> Nikhil Mehta | K13: =IF(J13<>"",COUNTIF(J$4:J13,"?*"),"") -> 7 | L13: =IFERROR(INDEX($J$4:$J$33,MATCH(ROWS(L$4:L13),$K$4:$K$33,0)),"") -> Rohan Desai
H14: Divya Reddy | I14: =IF(COUNTIF(High_Value_Customers!$B$8:$B$86,H14)>0,"Match","No match") -> No match | J14: =IF(I14="Match",H14,"") | K14: =IF(J14<>"",COUNTIF(J$4:J14,"?*"),"") | L14: =IFERROR(INDEX($J$4:$J$33,MATCH(ROWS(L$4:L14),$K$4:$K$33,0)),"") -> Divya Bhatt
A15: Most frequently purchased product | B15: =LEFT(F4&F5&F6&F7&F8&F9&F10&F11&F12&F13,LEN(F4&F5&F6&F7&F8&F9&F10&F11&F12&F13)-2) -> Monitor, Headphones | H15: Pooja Shah | I15: =IF(COUNTIF(High_Value_Customers!$B$8:$B$86,H15)>0,"Match","No match") -> No match | J15: =IF(I15="Match",H15,"") | K15: =IF(J15<>"",COUNTIF(J$4:J15,"?*"),"") | L15: =IFERROR(INDEX($J$4:$J$33,MATCH(ROWS(L$4:L15),$K$4:$K$33,0)),"") -> Rahul Chauhan
A16: Purchased (transactions) | B16: =MAX(B4:B13) -> 30 | H16: Pooja Nair | I16: =IF(COUNTIF(High_Value_Customers!$B$8:$B$86,H16)>0,"Match","No match") -> No match | J16: =IF(I16="Match",H16,"") | K16: =IF(J16<>"",COUNTIF(J$4:J16,"?*"),"") | L16: =IFERROR(INDEX($J$4:$J$33,MATCH(ROWS(L$4:L16),$K$4:$K$33,0)),"") -> Sanjay Reddy
A17: Top product by units sold | B17: =INDEX(A4:A13,MATCH(MAX(C4:C13),C4:C13,0)) -> Monitor | H17: Karan Desai | I17: =IF(COUNTIF(High_Value_Customers!$B$8:$B$86,H17)>0,"Match","No match") -> Match | J17: =IF(I17="Match",H17,"") -> Karan Desai | K17: =IF(J17<>"",COUNTIF(J$4:J17,"?*"),"") -> 8 | L17: =IFERROR(INDEX($J$4:$J$33,MATCH(ROWS(L$4:L17),$K$4:$K$33,0)),"") -> Priya Iyer
H18: Aditya Verma | I18: =IF(COUNTIF(High_Value_Customers!$B$8:$B$86,H18)>0,"Match","No match") -> Match | J18: =IF(I18="Match",H18,"") -> Aditya Verma | K18: =IF(J18<>"",COUNTIF(J$4:J18,"?*"),"") -> 9 | L18: =IFERROR(INDEX($J$4:$J$33,MATCH(ROWS(L$4:L18),$K$4:$K$33,0)),"") -> Meera Gupta
A19: Customers who bought more than once | B19: =COUNTIF(High_Value_Customers!$C$8:$C$86,">1") -> 70 | H19: Rohan Desai | I19: =IF(COUNTIF(High_Value_Customers!$B$8:$B$86,H19)>0,"Match","No match") -> Match | J19: =IF(I19="Match",H19,"") -> Rohan Desai | K19: =IF(J19<>"",COUNTIF(J$4:J19,"?*"),"") -> 10 | L19: =IFERROR(INDEX($J$4:$J$33,MATCH(ROWS(L$4:L19),$K$4:$K$33,0)),"") -> Amit Singh
A20: Most frequent customer (repeating name) | B20: =INDEX(High_Value_Customers!$B$8:$B$86,MATCH(MAX(High_Value_Customers!$C$8:$C$86),High_Value_Customers!$C$8:$C$86,0)) -> Riya Reddy | H20: Meera Bhatt | I20: =IF(COUNTIF(High_Value_Customers!$B$8:$B$86,H20)>0,"Match","No match") -> No match | J20: =IF(I20="Match",H20,"") | K20: =IF(J20<>"",COUNTIF(J$4:J20,"?*"),"") | L20: =IFERROR(INDEX($J$4:$J$33,MATCH(ROWS(L$4:L20),$K$4:$K$33,0)),"") -> Karan Iyer
A21: Their number of purchases | B21: =MAX(High_Value_Customers!$C$8:$C$86) -> 8 | H21: Divya Bhatt | I21: =IF(COUNTIF(High_Value_Customers!$B$8:$B$86,H21)>0,"Match","No match") -> Match | J21: =IF(I21="Match",H21,"") -> Divya Bhatt | K21: =IF(J21<>"",COUNTIF(J$4:J21,"?*"),"") -> 11 | L21: =IFERROR(INDEX($J$4:$J$33,MATCH(ROWS(L$4:L21),$K$4:$K$33,0)),"") -> Aditya Iyer
A22: Repeat share of transactions | B22: =COUNTIF('Final Project Dataset'!$P$2:$P$251,"Repeat")/COUNTA('Final Project Dataset'!$P$2:$P$251) -> 0.964 | H22: Rahul Chauhan | I22: =IF(COUNTIF(High_Value_Customers!$B$8:$B$86,H22)>0,"Match","No match") -> Match | J22: =IF(I22="Match",H22,"") -> Rahul Chauhan | K22: =IF(J22<>"",COUNTIF(J$4:J22,"?*"),"") -> 12 | L22: =IFERROR(INDEX($J$4:$J$33,MATCH(ROWS(L$4:L22),$K$4:$K$33,0)),"") -> Meera Mehta
H23: Sanjay Reddy | I23: =IF(COUNTIF(High_Value_Customers!$B$8:$B$86,H23)>0,"Match","No match") -> Match | J23: =IF(I23="Match",H23,"") -> Sanjay Reddy | K23: =IF(J23<>"",COUNTIF(J$4:J23,"?*"),"") -> 13 | L23: =IFERROR(INDEX($J$4:$J$33,MATCH(ROWS(L$4:L23),$K$4:$K$33,0)),"") -> Nikhil Reddy
H24: Priya Iyer | I24: =IF(COUNTIF(High_Value_Customers!$B$8:$B$86,H24)>0,"Match","No match") -> Match | J24: =IF(I24="Match",H24,"") -> Priya Iyer | K24: =IF(J24<>"",COUNTIF(J$4:J24,"?*"),"") -> 14 | L24: =IFERROR(INDEX($J$4:$J$33,MATCH(ROWS(L$4:L24),$K$4:$K$33,0)),"")
H25: Manish Sharma | I25: =IF(COUNTIF(High_Value_Customers!$B$8:$B$86,H25)>0,"Match","No match") -> No match | J25: =IF(I25="Match",H25,"") | K25: =IF(J25<>"",COUNTIF(J$4:J25,"?*"),"") | L25: =IFERROR(INDEX($J$4:$J$33,MATCH(ROWS(L$4:L25),$K$4:$K$33,0)),"")
H26: Meera Gupta | I26: =IF(COUNTIF(High_Value_Customers!$B$8:$B$86,H26)>0,"Match","No match") -> Match | J26: =IF(I26="Match",H26,"") -> Meera Gupta | K26: =IF(J26<>"",COUNTIF(J$4:J26,"?*"),"") -> 15 | L26: =IFERROR(INDEX($J$4:$J$33,MATCH(ROWS(L$4:L26),$K$4:$K$33,0)),"")
H27: Amit Singh | I27: =IF(COUNTIF(High_Value_Customers!$B$8:$B$86,H27)>0,"Match","No match") -> Match | J27: =IF(I27="Match",H27,"") -> Amit Singh | K27: =IF(J27<>"",COUNTIF(J$4:J27,"?*"),"") -> 16 | L27: =IFERROR(INDEX($J$4:$J$33,MATCH(ROWS(L$4:L27),$K$4:$K$33,0)),"")
H28: Ishita Patel | I28: =IF(COUNTIF(High_Value_Customers!$B$8:$B$86,H28)>0,"Match","No match") -> No match | J28: =IF(I28="Match",H28,"") | K28: =IF(J28<>"",COUNTIF(J$4:J28,"?*"),"") | L28: =IFERROR(INDEX($J$4:$J$33,MATCH(ROWS(L$4:L28),$K$4:$K$33,0)),"")
H29: Karan Iyer | I29: =IF(COUNTIF(High_Value_Customers!$B$8:$B$86,H29)>0,"Match","No match") -> Match | J29: =IF(I29="Match",H29,"") -> Karan Iyer | K29: =IF(J29<>"",COUNTIF(J$4:J29,"?*"),"") -> 17 | L29: =IFERROR(INDEX($J$4:$J$33,MATCH(ROWS(L$4:L29),$K$4:$K$33,0)),"")
H30: Aditya Iyer | I30: =IF(COUNTIF(High_Value_Customers!$B$8:$B$86,H30)>0,"Match","No match") -> Match | J30: =IF(I30="Match",H30,"") -> Aditya Iyer | K30: =IF(J30<>"",COUNTIF(J$4:J30,"?*"),"") -> 18 | L30: =IFERROR(INDEX($J$4:$J$33,MATCH(ROWS(L$4:L30),$K$4:$K$33,0)),"")
H31: Neha Sharma | I31: =IF(COUNTIF(High_Value_Customers!$B$8:$B$86,H31)>0,"Match","No match") -> No match | J31: =IF(I31="Match",H31,"") | K31: =IF(J31<>"",COUNTIF(J$4:J31,"?*"),"") | L31: =IFERROR(INDEX($J$4:$J$33,MATCH(ROWS(L$4:L31),$K$4:$K$33,0)),"")
H32: Meera Mehta | I32: =IF(COUNTIF(High_Value_Customers!$B$8:$B$86,H32)>0,"Match","No match") -> Match | J32: =IF(I32="Match",H32,"") -> Meera Mehta | K32: =IF(J32<>"",COUNTIF(J$4:J32,"?*"),"") -> 19 | L32: =IFERROR(INDEX($J$4:$J$33,MATCH(ROWS(L$4:L32),$K$4:$K$33,0)),"")
H33: Nikhil Reddy | I33: =IF(COUNTIF(High_Value_Customers!$B$8:$B$86,H33)>0,"Match","No match") -> Match | J33: =IF(I33="Match",H33,"") -> Nikhil Reddy | K33: =IF(J33<>"",COUNTIF(J$4:J33,"?*"),"") -> 20 | L33: =IFERROR(INDEX($J$4:$J$33,MATCH(ROWS(L$4:L33),$K$4:$K$33,0)),"")
H35: Matches found | I35: =COUNTIF(I4:I33,"Match") -> 20
H36: Not in customer list | I36: =COUNTIF(I4:I33,"No match") -> 10

Sheet Text_Abbrev
A1: Abbreviations with TEXT Functions
A2: LEFT, MID, FIND, UPPER, LOWER, PROPER, LEN, TEXT, concatenation
A3: Product | B3: 3-Letter Code | C3: Short Label | D3: Name Length | F3: Payment Method | G3: Initials (acronym) | H3: Region | I3: Region Code
A4: Laptop | B4: =UPPER(LEFT(A4,3)) -> LAP | C4: =UPPER(LEFT(A4,1))&LOWER(MID(A4,2,3))&"." -> Lapt. | D4: =LEN(A4) -> 6 | F4: Credit Card | G4: =IFERROR(UPPER(LEFT(F4,1)&MID(F4,FIND(" ",F4)+1,1)),UPPER(LEFT(F4,2))) -> CC | H4: North | I4: =UPPER(LEFT(H4,1))&"-"&UPPER(RIGHT(H4,1)) -> N-H
A5: Smartphone | B5: =UPPER(LEFT(A5,3)) -> SMA | C5: =UPPER(LEFT(A5,1))&LOWER(MID(A5,2,3))&"." -> Smar. | D5: =LEN(A5) -> 10 | F5: Debit Card | G5: =IFERROR(UPPER(LEFT(F5,1)&MID(F5,FIND(" ",F5)+1,1)),UPPER(LEFT(F5,2))) -> DC | H5: South | I5: =UPPER(LEFT(H5,1))&"-"&UPPER(RIGHT(H5,1)) -> S-H
A6: Monitor | B6: =UPPER(LEFT(A6,3)) -> MON | C6: =UPPER(LEFT(A6,1))&LOWER(MID(A6,2,3))&"." -> Moni. | D6: =LEN(A6) -> 7 | F6: UPI | G6: =IFERROR(UPPER(LEFT(F6,1)&MID(F6,FIND(" ",F6)+1,1)),UPPER(LEFT(F6,2))) -> UP | H6: East | I6: =UPPER(LEFT(H6,1))&"-"&UPPER(RIGHT(H6,1)) -> E-T
A7: Tablet | B7: =UPPER(LEFT(A7,3)) -> TAB | C7: =UPPER(LEFT(A7,1))&LOWER(MID(A7,2,3))&"." -> Tabl. | D7: =LEN(A7) -> 6 | F7: Cash | G7: =IFERROR(UPPER(LEFT(F7,1)&MID(F7,FIND(" ",F7)+1,1)),UPPER(LEFT(F7,2))) -> CA | H7: West | I7: =UPPER(LEFT(H7,1))&"-"&UPPER(RIGHT(H7,1)) -> W-T
A8: Smartwatch | B8: =UPPER(LEFT(A8,3)) -> SMA | C8: =UPPER(LEFT(A8,1))&LOWER(MID(A8,2,3))&"." -> Smar. | D8: =LEN(A8) -> 10 | F8: Net Banking | G8: =IFERROR(UPPER(LEFT(F8,1)&MID(F8,FIND(" ",F8)+1,1)),UPPER(LEFT(F8,2))) -> NB | H8: Central | I8: =UPPER(LEFT(H8,1))&"-"&UPPER(RIGHT(H8,1)) -> C-L
A9: Printer | B9: =UPPER(LEFT(A9,3)) -> PRI | C9: =UPPER(LEFT(A9,1))&LOWER(MID(A9,2,3))&"." -> Prin. | D9: =LEN(A9) -> 7
A10: Headphones | B10: =UPPER(LEFT(A10,3)) -> HEA | C10: =UPPER(LEFT(A10,1))&LOWER(MID(A10,2,3))&"." -> Head. | D10: =LEN(A10) -> 10
A11: Webcam | B11: =UPPER(LEFT(A11,3)) -> WEB | C11: =UPPER(LEFT(A11,1))&LOWER(MID(A11,2,3))&"." -> Webc. | D11: =LEN(A11) -> 6
A12: Keyboard | B12: =UPPER(LEFT(A12,3)) -> KEY | C12: =UPPER(LEFT(A12,1))&LOWER(MID(A12,2,3))&"." -> Keyb. | D12: =LEN(A12) -> 8
A13: Mouse | B13: =UPPER(LEFT(A13,3)) -> MOU | C13: =UPPER(LEFT(A13,1))&LOWER(MID(A13,2,3))&"." -> Mous. | D13: =LEN(A13) -> 5
A15: Customer Name | B15: Initials | C15: Display Name | D15: Txn Code (sample)
A16: =High_Value_Customers!B8 -> Rahul Joshi | B16: =LEFT(A16,1)&MID(A16,FIND(" ",A16)+1,1) -> RJ | C16: =UPPER(LEFT(A16,1))&". "&PROPER(MID(A16,FIND(" ",A16)+1,50)) -> R. Joshi | D16: ='Final Project Dataset'!Q2 -> HEA-0125-07390
A17: =High_Value_Customers!B9 -> Karan Bhatt | B17: =LEFT(A17,1)&MID(A17,FIND(" ",A17)+1,1) -> KB | C17: =UPPER(LEFT(A17,1))&". "&PROPER(MID(A17,FIND(" ",A17)+1,50)) -> K. Bhatt | D17: ='Final Project Dataset'!Q3 -> PRI-0125-09403
A18: =High_Value_Customers!B10 -> Kavya Reddy | B18: =LEFT(A18,1)&MID(A18,FIND(" ",A18)+1,1) -> KR | C18: =UPPER(LEFT(A18,1))&". "&PROPER(MID(A18,FIND(" ",A18)+1,50)) -> K. Reddy | D18: ='Final Project Dataset'!Q4 -> TAB-0125-34624
A19: =High_Value_Customers!B11 -> Vihaan Nair | B19: =LEFT(A19,1)&MID(A19,FIND(" ",A19)+1,1) -> VN | C19: =UPPER(LEFT(A19,1))&". "&PROPER(MID(A19,FIND(" ",A19)+1,50)) -> V. Nair | D19: ='Final Project Dataset'!Q5 -> WEB-0125-08751
A20: =High_Value_Customers!B12 -> Aditya Joshi | B20: =LEFT(A20,1)&MID(A20,FIND(" ",A20)+1,1) -> AJ | C20: =UPPER(LEFT(A20,1))&". "&PROPER(MID(A20,FIND(" ",A20)+1,50)) -> A. Joshi | D20: ='Final Project Dataset'!Q6 -> SMA-0125-42690
A21: =High_Value_Customers!B13 -> Riya Shah | B21: =LEFT(A21,1)&MID(A21,FIND(" ",A21)+1,1) -> RS | C21: =UPPER(LEFT(A21,1))&". "&PROPER(MID(A21,FIND(" ",A21)+1,50)) -> R. Shah | D21: ='Final Project Dataset'!Q7 -> HEA-0125-18590
A22: =High_Value_Customers!B14 -> Rohan Sharma | B22: =LEFT(A22,1)&MID(A22,FIND(" ",A22)+1,1) -> RS | C22: =UPPER(LEFT(A22,1))&". "&PROPER(MID(A22,FIND(" ",A22)+1,50)) -> R. Sharma | D22: ='Final Project Dataset'!Q8 -> KEY-0125-01978
A23: =High_Value_Customers!B15 -> Amit Singh | B23: =LEFT(A23,1)&MID(A23,FIND(" ",A23)+1,1) -> AS | C23: =UPPER(LEFT(A23,1))&". "&PROPER(MID(A23,FIND(" ",A23)+1,50)) -> A. Singh | D23: ='Final Project Dataset'!Q9 -> KEY-0125-05469
A24: =High_Value_Customers!B16 -> Sanjay Reddy | B24: =LEFT(A24,1)&MID(A24,FIND(" ",A24)+1,1) -> SR | C24: =UPPER(LEFT(A24,1))&". "&PROPER(MID(A24,FIND(" ",A24)+1,50)) -> S. Reddy | D24: ='Final Project Dataset'!Q10 -> LAP-0125-46180
A25: =High_Value_Customers!B17 -> Vihaan Bhatt | B25: =LEFT(A25,1)&MID(A25,FIND(" ",A25)+1,1) -> VB | C25: =UPPER(LEFT(A25,1))&". "&PROPER(MID(A25,FIND(" ",A25)+1,50)) -> V. Bhatt | D25: ='Final Project Dataset'!Q11 -> SMA-0125-08460
A27: Txn Code format: PRODUCT(3 letters) - MMYY - SALES(5 digits), e.g. =UPPER(LEFT(C2,3))&"-"&TEXT(B2,"MMYY")&"-"&TEXT(F2,"00000")

Sheet Date_Time
A1: Date & Time Functions
A2: TODAY, NOW, DATEDIF, EOMONTH, timestamp with iterative calculation
A3: TODAY() | B3: =TODAY() -> 46325
A4: NOW() | B4: =NOW() -> 46325.669
A5: First transaction date | B5: =MIN('Final Project Dataset'!$B$2:$B$251) -> 45658
A6: Last transaction date | B6: =MAX('Final Project Dataset'!$B$2:$B$251) -> 46021
A7: Dataset span (DATEDIF y / ym / md) | B7: =DATEDIF(B5,B6,"y")&" yrs "&DATEDIF(B5,B6,"ym")&" mths "&DATEDIF(B5,B6,"md")&" days" -> 0 yrs 11 mths 29 days
A8: Time since last transaction (DATEDIF) | B8: =DATEDIF(B6,B3,"y")&" yrs "&DATEDIF(B6,B3,"ym")&" mths "&DATEDIF(B6,B3,"md")&" days" -> 0 yrs 10 mths 0 days
A9: Month-end of last transaction (EOMONTH 0) | B9: =EOMONTH(B6,0) -> 46022
A10: Previous month-end (EOMONTH -1) | B10: =EOMONTH(B6,-1) -> 45991
A11: Next month-end (EOMONTH +1) | B11: =EOMONTH(B6,1) -> 46053
A12: Days left in current month | B12: =EOMONTH(B3,0)-B3 -> 1
A13: Quarter-end of first transaction | B13: =EOMONTH(B5,2-MOD(MONTH(B5)-1,3)) -> 45747
A14: Avg days between transactions | B14: =(B6-B5)/(COUNT('Final Project Dataset'!$B$2:$B$251)-1) -> 1.4578313
A17: Auto-Timestamp =IF(A<>"",IF(OR(B="",B=0),NOW(),B),"") — needs iterative calculation (already ON in this file)
A18: Type an entry here | B18: Timestamp (frozen at entry) | C18: Note
A19: Order verified | B19: =IF(A19<>"",IF(OR(B19="",B19=0),NOW(),B19),"") -> 46325.425 | C19: Timestamp stays fixed after it is stamped. To re-stamp, clear the entry and retype it.
A20: Invoice generated | B20: =IF(A20<>"",IF(OR(B20="",B20=0),NOW(),B20),"") -> 46325.425 | C20: If Excel warns about circular references: File > Options > Formulas > Enable iterative calculation.
A21: Payment received | B21: =IF(A21<>"",IF(OR(B21="",B21=0),NOW(),B21),"") -> 46325.425
B22: =IF(A22<>"",IF(OR(B22="",B22=0),NOW(),B22),"")
B23: =IF(A23<>"",IF(OR(B23="",B23=0),NOW(),B23),"")
B24: =IF(A24<>"",IF(OR(B24="",B24=0),NOW(),B24),"")
B25: =IF(A25<>"",IF(OR(B25="",B25=0),NOW(),B25),"")
B26: =IF(A26<>"",IF(OR(B26="",B26=0),NOW(),B26),"")

Sheet WhatIf
A1: What-If Analysis: Scenario Manager & Goal Seek
A2: Blue cells on yellow are inputs. Scenario Manager scenarios are stored on cells B11:B13.
A3: Baseline (from dataset) | D3: Scenario comparison (all computed live)
A4: Total sales | B4: =SUM('Final Project Dataset'!$F$2:$F$251) -> 5262053 | D4: Parameter | E4: Base | F4: Optimistic | G4: Pessimistic
A5: Total profit | B5: =SUM('Final Project Dataset'!$H$2:$H$251) -> 800178.26 | D5: Price change % | E5: 0 | F5: 0.05 | G5: -0.05
A6: Total cost (sales − profit) | B6: =B4-B5 -> 4461874.7 | D6: Volume change % | E6: 0 | F6: 0.1 | G6: -0.1
A7: Units sold | B7: =SUM('Final Project Dataset'!$D$2:$D$251) -> 484 | D7: Cost change % | E7: 0 | F7: -0.03 | G7: 0.05
D9: Sales | E9: =$B$4*(1+E5)*(1+E6) -> 5262053 | F9: =$B$4*(1+F5)*(1+F6) -> 6077671.2 | G9: =$B$4*(1+G5)*(1+G6) -> 4499055.3
A10: Changing cells (Scenario Manager / Goal Seek) | D10: Cost | E10: =$B$6*(1+E6)*(1+E7) -> 4461874.7 | F10: =$B$6*(1+F6)*(1+F7) -> 4760820.3 | G10: =$B$6*(1+G6)*(1+G7) -> 4216471.6
A11: Price change % | B11: 0 | D11: Profit | E11: =E9-E10 -> 800178.26 | F11: =F9-F10 -> 1316850.9 | G11: =G9-G10 -> 282583.69
A12: Volume change % | B12: 0 | D12: Margin | E12: =IF(E9=0,0,E11/E9) -> 0.15206579 | F12: =IF(F9=0,0,F11/F9) -> 0.2166703 | G12: =IF(G9=0,0,G11/G9) -> 0.06280956
A13: Cost change % | B13: 0 | D13: Profit vs baseline | E13: =E11/$B$5-1 -> 0 | F13: =F11/$B$5-1 -> 0.64569688 | G13: =G11/$B$5-1 -> -0.64684908
A15: Model output
A16: New sales | B16: =B4*(1+B11)*(1+B12) -> 5262053
A17: New cost | B17: =B6*(1+B12)*(1+B13) -> 4461874.7 | D17: Goal Seek in Excel: Data > What-If Analysis > Goal Seek
A18: New profit | B18: =B16-B17 -> 800178.26 | D18: Set cell: B18 To value: =B25's value By changing cell: B12
A19: New margin | B19: =IF(B16=0,0,B18/B16) -> 0.15206579 | D19: The result will match B26 above (the closed-form answer).
A20: Profit vs baseline | B20: =B18/B5-1 -> 0
D21: Scenario Manager: Data > What-If Analysis > Scenario Manager
D22: Base, Optimistic and Pessimistic are pre-defined on B11:B13; click Show to apply.
A23: Goal Seek: profit target
A24: Desired profit uplift | B24: 0.2
A25: Target profit | B25: =B5*(1+B24) -> 960213.91
A26: Required volume change (closed form) | B26: =B25/(B4*(1+B11)-B6*(1+B13))-1 -> 0.2
A27: Profit at that volume | B27: =(1+B26)*(B4*(1+B11)-B6*(1+B13)) -> 960213.91
A28: Check (should be 0) | B28: =ROUND(B27-B25,2) -> 0

Sheet Regression
A1: Linear Regression: Profit (Y) on Sales (X)
A2: Same layout as Data Analysis ToolPak output, built with formulas so it stays live.
A3: Regression Statistics
A4: Multiple R | B4: =SQRT(B5) -> 0.94524319
A5: R Square | B5: =RSQ('Final Project Dataset'!$H$2:$H$251,'Final Project Dataset'!$F$2:$F$251) -> 0.89348469
A6: Adjusted R Square | B6: =1-(1-B5)*(B8-1)/(B8-2) -> 0.89305519
A7: Standard Error | B7: =STEYX('Final Project Dataset'!$H$2:$H$251,'Final Project Dataset'!$F$2:$F$251) -> 1251.8111
A8: Observations | B8: =COUNT('Final Project Dataset'!$F$2:$F$251) -> 250
A10: ANOVA
B11: df | C11: SS | D11: MS | E11: F | F11: Significance F
A12: Regression | B12: 1 | C12: =B5*DEVSQ('Final Project Dataset'!$H$2:$H$251) -> 3.2599008e+09 | D12: =C12/B12 -> 3.2599008e+09 | E12: =D12/D13 -> 2080.3038 | F12: =FDIST(E12,B12,B13) -> 1.3415858e-122
A13: Residual | B13: =B8-2 -> 248 | C13: =C14-C12 -> 3.8862372e+08 | D13: =C13/B13 -> 1567031.1
A14: Total | B14: =B8-1 -> 249 | C14: =DEVSQ('Final Project Dataset'!$H$2:$H$251) -> 3.6485246e+09
B16: Coefficients | C16: Standard Error | D16: t Stat | E16: P-value | F16: Lower 95% | G16: Upper 95%
A17: Intercept | B17: =INTERCEPT('Final Project Dataset'!$H$2:$H$251,'Final Project Dataset'!$F$2:$F$251) -> 317.96248 | C17: =B7*SQRT(1/B8+AVERAGE('Final Project Dataset'!$F$2:$F$251)^2/DEVSQ('Final Project Dataset'!$F$2:$F$251)) -> 101.30575 | D17: =B17/C17 -> 3.1386421 | E17: =TDIST(ABS(D17),$B$13,2) -> 0.0019027543 | F17: =B17-TINV(0.05,$B$13)*C17 -> 118.43315 | G17: =B17+TINV(0.05,$B$13)*C17 -> 517.49181
A18: Sales (X variable) | B18: =SLOPE('Final Project Dataset'!$H$2:$H$251,'Final Project Dataset'!$F$2:$F$251) -> 0.1369594 | C18: =B7/SQRT(DEVSQ('Final Project Dataset'!$F$2:$F$251)) -> 0.0030028143 | D18: =B18/C18 -> 45.610347 | E18: =TDIST(ABS(D18),$B$13,2) -> 1.3415858e-122 | F18: =B18-TINV(0.05,$B$13)*C18 -> 0.13104513 | G18: =B18+TINV(0.05,$B$13)*C18 -> 0.14287367
A20: Prediction
A21: Sales amount (₹) | B21: 50000
A22: Predicted profit (₹) | B22: =B17+B18*B21 -> 7165.9327
A23: Interpretation | B23: ="Every extra ₹1,000 of sales adds about ₹"&TEXT(B18*1000,"#,##0")&" of profit; sales explain "&TEXT(B5,"0.0%")&" of profit variation." -> Every extra ₹1,000 of sales adds about ₹137 of profit; sales explain 89.3% of profit variation.

Sheet HowTo
A1: How to build the native-Excel versions
A2: This workbook delivers each requirement with formulas that work everywhere; these steps add the interactive Excel-only objects.
A3: Requirement | B3: Built in this workbook | C3: Native Excel steps
A4: PivotTables | B4: Pivot_Tables sheet (SUMIFS/COUNTIFS, reacts to dashboard filters) | C4: Select any cell in 'Final Project Dataset' > Insert > PivotTable > New Worksheet. Drag product to Rows and sales/profit to Values.
A5: Pivot Charts (Bar, Line, Pie) | B5: Bar, line, pie and column charts on Dashboard | C5: Click inside the PivotTable > PivotTable Analyze > PivotChart, then pick Bar, Line or Pie.
A6: Slicers | B6: Region and Product drop-downs on Dashboard | C6: Click the PivotTable > PivotTable Analyze > Insert Slicer > tick Region, Product.
A7: Timeline | B7: From / To date cells on Dashboard | C7: Click the PivotTable > PivotTable Analyze > Insert Timeline > Date.
A8: FILTER function | B8: FILTER_Demo sheet (helper columns + INDEX/MATCH) | C8: In Excel 365: =FILTER(A2:K251,(G2:G251="West")*(C2:C251="Laptop"),"No match").
A9: Scenario Manager | B9: Base / Optimistic / Pessimistic stored on WhatIf!B11:B13 | C9: Data > What-If Analysis > Scenario Manager > select a scenario > Show.
A10: Goal Seek | B10: Closed-form answer in WhatIf!B26 | C10: Data > What-If Analysis > Goal Seek: Set cell B18, To value = target profit (B25), By changing B12.
A11: Data Analysis ToolPak regression | B11: Regression sheet reproduces the ToolPak output with formulas | C11: File > Options > Add-ins > Analysis ToolPak > Go. Then Data > Data Analysis > Regression, Y = profit, X = sales.
A12: Iterative timestamp | B12: Date_Time sheet, iterative calc already enabled | C12: File > Options > Formulas > Enable iterative calculation; use =IF(A1<>"",IF(B1="",NOW(),B1),"").
